Workbook

Sheet README
A1: Music League Song Tracker
A2: Rebuilt tracker: one Votes table, Spotify URIs as the join key, formula-driven checks and analytics. Your original file is unchanged.
A4: Tabs
A5: Checks | B5: Live validation. Should read ALL PASS. Forfeits and zero-vote songs appear as INFO.
A6: All Song Rankings | B6: One row per submission (table tbl_music). A:G, I and L:M are inputs; gray columns are formulas. Place is per league and round.
A7: Votes | B7: One row per non-zero vote (table tbl_votes). Inputs: League #, Round #, Voter, Spotify URI, Points. Gray columns look up the song.
A8: Rounds | B8: One row per round: names, descriptions, point budget, songs per person, max votes per song. Budget, songs per person, and max votes per song are typed inputs.
A9: Participants | B9: Names as used in the workbook, plus export usernames for matching future imports.
A10: Music League Analytics | B10: League and genre summaries. Formulas only.
A11: Repeated Songs | B11: Songs submitted more than once. Formulas only.
A12: Lists | B12: Allowed genres (drives the dropdown) and the Genre-to-Major-Genre mapping used for the recap.
A13: Retired Artist / Retired Songs / Aliases | B13: Copied unchanged from the original.
A14: Change Log | B14: Every repair and structural change, with before/after.
A16: Adding a league
B17: 1. Rounds: add one row per round. League must match the text you will use in All Song Rankings column I exactly.
B18: 2. All Song Rankings: paste submissions under the last row (Song, Artist, Genre, Submitter, Round as 'N - Name', League, Spotify URI from the export's submissions file). Leave Points and # of Voters blank until the round is scored. Copy the gray formula cells down from the row above.
B19: 3. Votes: paste votes from the export (League #, Round #, Voter first name, Spotify URI, Points). Include only rows with Points above 0 and not the submitter's own song. Copy the gray formula cells down.
B20: 4. Participants: add anyone new (first name, plus export username).
B21: 5. Checks: confirm ALL PASS. Use paste-values for text containing numbers; never fill down on titles or artists (this is what corrupted names like 'Eiffel 65' before).
A23: Conventions and limits
B24: Gray cells are formulas. Don't type over them.
B25: Forfeited = the submitter cast no votes in that round and the official points are zero. This held for all 40 such songs in Leagues 1 to 7.
B26: Points and # of Voters in All Song Rankings are typed from the Music League results. Raw Points are computed from Votes; Status flags any disagreement.
B27: Repeat Count flags a song submitted more than once: same Spotify URI, or same Song + Artist text (which also covers rows with no URI yet). COUNTIF treats * and ? in titles as wildcards.
B28: Checks and Analytics use fixed ranges (rankings to row 5000, votes to row 20000, participants to row 200). Extend them if the workbook outgrows that.
B29: Data sources: Votes come from the Music League exports for Leagues 1 to 7, plus 6 ballot rows for League 2 round 7 kept from your original tab. Spotify URIs come from the exports. Points were typed in your original file.

Sheet Checks
A1: Workbook checks
A2: Live formulas. Expected-zero checks should read PASS. INFO rows are counts to be aware of, not errors.
A3: Overall | B3: =IF(COUNTIF(D6:D22,"FAIL")=0,IF(COUNTIF(D6:D22,"REVIEW")=0,"ALL PASS","PASS, with items to review"),"FAIL: see below") -> PASS, with items to review
A5: Check | B5: Value | C5: Expected | D5: Result
A6: Vote rows | B6: =COUNTA(Votes!$A:$A)-1 -> 5288 | D6: INFO
A7: Vote rows not found in rankings (Spotify URI + league + round) | B7: =COUNTIF(Votes!$J:$J,"NOT FOUND") -> 0 | C7: 0 | D7: =IF(B7=C7,"PASS","FAIL") -> PASS
A8: Self-votes | B8: =COUNTIF(Votes!$J:$J,"SELF-VOTE") -> 0 | C8: 0 | D8: =IF(B8=C8,"PASS","FAIL") -> PASS
A9: Duplicate vote rows | B9: =COUNTIF(Votes!$J:$J,"DUPLICATE") -> 0 | C9: 0 | D9: =IF(B9=C9,"PASS","FAIL") -> PASS
A10: Songs where typed Points / # of Voters disagree with the votes (Mismatch) | B10: =COUNTIF('All Song Rankings'!$Q:$Q,"Mismatch") -> 0 | C10: 0 | D10: =IF(B10=C10,"PASS","FAIL") -> PASS
A11: Scored songs with no Spotify URI | B11: =COUNTIF('All Song Rankings'!$Q:$Q,"No URI") -> 0 | C11: 0 | D11: =IF(B11=C11,"PASS","FAIL") -> PASS
A12: Rows whose League is missing from the Rounds tab | B12: =COUNTIF('All Song Rankings'!$J:$J,"ADD LEAGUE TO ROUNDS") -> 0 | C12: 0 | D12: =IF(B12=C12,"PASS","FAIL") -> PASS
A13: Scored songs with no Place | B13: =COUNTIFS('All Song Rankings'!$F:$F,">=0",'All Song Rankings'!$N:$N,"") -> 0 | C13: 0 | D13: =IF(B13=C13,"PASS","FAIL") -> PASS
A14: Genres not on the Lists tab | B14: =SUMPRODUCT(--('All Song Rankings'!$C$2:$C$5000<>""),--(COUNTIF(Lists!$A:$A,'All Song Rankings'!$C$2:$C$5000)=0)) -> 7 | C14: 0 | D14: =IF(B14=C14,"PASS","REVIEW") -> REVIEW
A15: Genre labels with no Major Genre mapping | B15: =COUNTIF('All Song Rankings'!$U:$U,"Unmapped") -> 0 | C15: 0 | D15: =IF(B15=C15,"PASS","FAIL") -> PASS
A16: Submitters not on the Participants tab | B16: =SUMPRODUCT(--('All Song Rankings'!$D$2:$D$5000<>""),--(COUNTIF(Participants!$A:$A,'All Song Rankings'!$D$2:$D$5000)=0)) -> 0 | C16: 0 | D16: =IF(B16=C16,"PASS","FAIL") -> PASS
A17: Voters not on the Participants tab | B17: =SUMPRODUCT(--(Votes!$C$2:$C$20000<>""),--(COUNTIF(Participants!$A:$A,Votes!$C$2:$C$20000)=0)) -> 0 | C17: 0 | D17: =IF(B17=C17,"PASS","FAIL") -> PASS
A18: Total vote points minus raw points matched to songs | B18: =SUM(Votes!$E:$E)-SUM('All Song Rankings'!$O:$O) -> 0 | C18: 0 | D18: =IF(B18=C18,"PASS","FAIL") -> PASS
A19: Forfeited songs (submitter did not vote; official points zeroed) | B19: =COUNTIF('All Song Rankings'!$Q:$Q,"Forfeited") -> 40 | D19: INFO
A20: Zero-vote songs (no votes recorded) | B20: =COUNTIF('All Song Rankings'!$Q:$Q,"Zero-vote") -> 8 | D20: INFO
A21: Unscored songs (league in progress) | B21: =COUNTIF('All Song Rankings'!$Q:$Q,"Unscored") -> 30 | D21: INFO
A22: Official points lost to forfeits (raw minus official, scored songs) | B22: =SUM('All Song Rankings'!$O:$O)-SUMIFS('All Song Rankings'!$F:$F,'All Song Rankings'!$L:$L,"<>") -> 332 | D22: INFO

Sheet All Song Rankings
A1: Song | B1: Artist | C1: Genre | D1: Submitter | E1: Round | F1: Points | G1: # of Voters | H1: Place | I1: League | J1: League # | K1: Round # | L1: Spotify URI | M1: Subgenre | N1: Place # | O1: Raw Points | P1: Raw Voters | Q1: Status | R1: Repeat Count | S1: Repeat Seq | T1: Key | U1: Major Genre
A2: Love Me to Heaven | B2: Jonas Brothers | C2: Pop | D2: Kelsey | E2: 1 - A Song you'd recommend any day | F2: 16 | G2: 10 | H2: =IF(N2="","",N2&IF(AND(MOD(N2,100)>=11,MOD(N2,100)<=13),"th",CHOOSE(MIN(5,MOD(N2,10)+1),"th","st","nd","rd","th"))) -> 1st | I2: Org Mgmt COE (1st League) | J2: =IFERROR(INDEX(Rounds!$A:$A,MATCH(I2,Rounds!$B:$B,0)),"ADD LEAGUE TO ROUNDS") -> 1 | K2: =IFERROR(VALUE(LEFT(E2,FIND(" - ",E2)-1)),"") -> 1 | L2: spotify:track:7usqgT1ajVAJ3s0wXePtRr | N2: =IF(F2="","",1+COUNTIFS($J:$J,J2,$K:$K,K2,$F:$F,">"&F2)+COUNTIFS($J:$J,J2,$K:$K,K2,$F:$F,F2,$G:$G,">"&G2)) -> 1 | O2: =IF(L2="","",SUMIFS(Votes!$E:$E,Votes!$A:$A,J2,Votes!$B:$B,K2,Votes!$D:$D,L2)) -> 16 | P2: =IF(L2="","",COUNTIFS(Votes!$A:$A,J2,Votes!$B:$B,K2,Votes!$D:$D,L2)) -> 10 | Q2: =IF(F2="","Unscored",IF(O2="","No URI",IF(AND(F2=0,O2=0),"Zero-vote",IF(AND(F2=O2,G2=P2),"OK",IF(AND(F2=0,O2>0,COUNTIFS(Votes!$A:$A,J2,Votes!$B:$B,K2,Votes!$C:$C,D2)=0),"Forfeited","Mismatch"))))) -> OK | R2: =MAX(IF(L2<>"",COUNTIF($L:$L,L2),0),COUNTIFS($A:$A,A2,$B:$B,B2)) -> 1 | S2: =IF(R2>1,COUNTIF($R$2:R2,">1"),"") | T2: =IF(L2="","",J2&"|"&K2&"|"&L2) -> 1|1|spotify:track:7usqgT1ajVAJ3s0wXePtRr | U2: =IF(C2="","",IFERROR(INDEX(Lists!$F:$F,MATCH(C2,Lists!$E:$E,0)),"Unmapped")) -> Pop
A3: Shut Up and Dance | B3: WALK THE MOON | C3: Rock | D3: Nicole | E3: 1 - A Song you'd recommend any day | F3: 16 | G3: 9 | H3: =IF(N3="","",N3&IF(AND(MOD(N3,100)>=11,MOD(N3,100)<=13),"th",CHOOSE(MIN(5,MOD(N3,10)+1),"th","st","nd","rd","th"))) -> 2nd | I3: Org Mgmt COE (1st League) | J3: =IFERROR(INDEX(Rounds!$A:$A,MATCH(I3,Rounds!$B:$B,0)),"ADD LEAGUE TO ROUNDS") -> 1 | K3: =IFERROR(VALUE(LEFT(E3,FIND(" - ",E3)-1)),"") -> 1 | L3: spotify:track:4kbj5MwxO1bq9wjT5g9HaA | N3: =IF(F3="","",1+COUNTIFS($J:$J,J3,$K:$K,K3,$F:$F,">"&F3)+COUNTIFS($J:$J,J3,$K:$K,K3,$F:$F,F3,$G:$G,">"&G3)) -> 2 | O3: =IF(L3="","",SUMIFS(Votes!$E:$E,Votes!$A:$A,J3,Votes!$B:$B,K3,Votes!$D:$D,L3)) -> 16 | P3: =IF(L3="","",COUNTIFS(Votes!$A:$A,J3,Votes!$B:$B,K3,Votes!$D:$D,L3)) -> 9 | Q3: =IF(F3="","Unscored",IF(O3="","No URI",IF(AND(F3=0,O3=0),"Zero-vote",IF(AND(F3=O3,G3=P3),"OK",IF(AND(F3=0,O3>0,COUNTIFS(Votes!$A:$A,J3,Votes!$B:$B,K3,Votes!$C:$C,D3)=0),"Forfeited","Mismatch"))))) -> OK | R3: =MAX(IF(L3<>"",COUNTIF($L:$L,L3),0),COUNTIFS($A:$A,A3,$B:$B,B3)) -> 2 | S3: =IF(R3>1,COUNTIF($R$2:R3,">1"),"") -> 1 | T3: =IF(L3="","",J3&"|"&K3&"|"&L3) -> 1|1|spotify:track:4kbj5MwxO1bq9wjT5g9HaA | U3: =IF(C3="","",IFERROR(INDEX(Lists!$F:$F,MATCH(C3,Lists!$E:$E,0)),"Unmapped")) -> Rock
A4: Fantasy | B4: Mariah Carey | C4: R&B/Soul | D4: Stephanie | E4: 1 - A Song you'd recommend any day | F4: 12 | G4: 7 | H4: =IF(N4="","",N4&IF(AND(MOD(N4,100)>=11,MOD(N4,100)<=13),"th",CHOOSE(MIN(5,MOD(N4,10)+1),"th","st","nd","rd","th"))) -> 3rd | I4: Org Mgmt COE (1st League) | J4: =IFERROR(INDEX(Rounds!$A:$A,MATCH(I4,Rounds!$B:$B,0)),"ADD LEAGUE TO ROUNDS") -> 1 | K4: =IFERROR(VALUE(LEFT(E4,FIND(" - ",E4)-1)),"") -> 1 | L4: spotify:track:6xkryXuiZU360Lngd4sx13 | N4: =IF(F4="","",1+COUNTIFS($J:$J,J4,$K:$K,K4,$F:$F,">"&F4)+COUNTIFS($J:$J,J4,$K:$K,K4,$F:$F,F4,$G:$G,">"&G4)) -> 3 | O4: =IF(L4="","",SUMIFS(Votes!$E:$E,Votes!$A:$A,J4,Votes!$B:$B,K4,Votes!$D:$D,L4)) -> 12 | P4: =IF(L4="","",COUNTIFS(Votes!$A:$A,J4,Votes!$B:$B,K4,Votes!$D:$D,L4)) -> 7 | Q4: =IF(F4="","Unscored",IF(O4="","No URI",IF(AND(F4=0,O4=0),"Zero-vote",IF(AND(F4=O4,G4=P4),"OK",IF(AND(F4=0,O4>0,COUNTIFS(Votes!$A:$A,J4,Votes!$B:$B,K4,Votes!$C:$C,D4)=0),"Forfeited","Mismatch"))))) -> OK | R4: =MAX(IF(L4<>"",COUNTIF($L:$L,L4),0),COUNTIFS($A:$A,A4,$B:$B,B4)) -> 2 | S4: =IF(R4>1,COUNTIF($R$2:R4,">1"),"") -> 2 | T4: =IF(L4="","",J4&"|"&K4&"|"&L4) -> 1|1|spotify:track:6xkryXuiZU360Lngd4sx13 | U4: =IF(C4="","",IFERROR(INDEX(Lists!$F:$F,MATCH(C4,Lists!$E:$E,0)),"Unmapped")) -> R&B/Soul
A5: Lonely Heart | B5: 5 Seconds of Summer | C5: Rock | D5: Merita | E5: 1 - A Song you'd recommend any day | F5: 12 | G5: 7 | H5: =IF(N5="","",N5&IF(AND(MOD(N5,100)>=11,MOD(N5,100)<=13),"th",CHOOSE(MIN(5,MOD(N5,10)+1),"th","st","nd","rd","th"))) -> 3rd | I5: Org Mgmt COE (1st League) | J5: =IFERROR(INDEX(Rounds!$A:$A,MATCH(I5,Rounds!$B:$B,0)),"ADD LEAGUE TO ROUNDS") -> 1 | K5: =IFERROR(VALUE(LEFT(E5,FIND(" - ",E5)-1)),"") -> 1 | L5: spotify:track:1MAXdOA4Dtz6eJMz0nEq2H | N5: =IF(F5="","",1+COUNTIFS($J:$J,J5,$K:$K,K5,$F:$F,">"&F5)+COUNTIFS($J:$J,J5,$K:$K,K5,$F:$F,F5,$G:$G,">"&G5)) -> 3 | O5: =IF(L5="","",SUMIFS(Votes!$E:$E,Votes!$A:$A,J5,Votes!$B:$B,K5,Votes!$D:$D,L5)) -> 12 | P5: =IF(L5="","",COUNTIFS(Votes!$A:$A,J5,Votes!$B:$B,K5,Votes!$D:$D,L5)) -> 7 | Q5: =IF(F5="","Unscored",IF(O5="","No URI",IF(AND(F5=0,O5=0),"Zero-vote",IF(AND(F5=O5,G5=P5),"OK",IF(AND(F5=0,O5>0,COUNTIFS(Votes!$A:$A,J5,Votes!$B:$B,K5,Votes!$C:$C,D5)=0),"Forfeited","Mismatch"))))) -> OK | R5: =MAX(IF(L5<>"",COUNTIF($L:$L,L5),0),COUNTIFS($A:$A,A5,$B:$B,B5)) -> 1 | S5: =IF(R5>1,COUNTIF($R$2:R5,">1"),"") | T5: =IF(L5="","",J5&"|"&K5&"|"&L5) -> 1|1|spotify:track:1MAXdOA4Dtz6eJMz0nEq2H | U5: =IF(C5="","",IFERROR(INDEX(Lists!$F:$F,MATCH(C5,Lists!$E:$E,0)),"Unmapped")) -> Rock
A6: Euclid | B6: Sleep Token | C6: Metal | D6: Kristen | E6: 1 - A Song you'd recommend any day | F6: 11 | G6: 6 | H6: =IF(N6="","",N6&IF(AND(MOD(N6,100)>=11,MOD(N6,100)<=13),"th",CHOOSE(MIN(5,MOD(N6,10)+1),"th","st","nd","rd","th"))) -> 5th | I6: Org Mgmt COE (1st League) | J6: =IFERROR(INDEX(Rounds!$A:$A,MATCH(I6,Rounds!$B:$B,0)),"ADD LEAGUE TO ROUNDS") -> 1 | K6: =IFERROR(VALUE(LEFT(E6,FIND(" - ",E6)-1)),"") -> 1 | L6: spotify:track:3hZIvVYZWsuFpdWdXQFgKx | N6: =IF(F6="","",1+COUNTIFS($J:$J,J6,$K:$K,K6,$F:$F,">"&F6)+COUNTIFS($J:$J,J6,$K:$K,K6,$F:$F,F6,$G:$G,">"&G6)) -> 5 | O6: =IF(L6="","",SUMIFS(Votes!$E:$E,Votes!$A:$A,J6,Votes!$B:$B,K6,Votes!$D:$D,L6)) -> 11 | P6: =IF(L6="","",COUNTIFS(Votes!$A:$A,J6,Votes!$B:$B,K6,Votes!$D:$D,L6)) -> 6 | Q6: =IF(F6="","Unscored",IF(O6="","No URI",IF(AND(F6=0,O6=0),"Zero-vote",IF(AND(F6=O6,G6=P6),"OK",IF(AND(F6=0,O6>0,COUNTIFS(Votes!$A:$A,J6,Votes!$B:$B,K6,Votes!$C:$C,D6)=0),"Forfeited","Mismatch"))))) -> OK | R6: =MAX(IF(L6<>"",COUNTIF($L:$L,L6),0),COUNTIFS($A:$A,A6,$B:$B,B6)) -> 1 | S6: =IF(R6>1,COUNTIF($R$2:R6,">1"),"") | T6: =IF(L6="","",J6&"|"&K6&"|"&L6) -> 1|1|spotify:track:3hZIvVYZWsuFpdWdXQFgKx | U6: =IF(C6="","",IFERROR(INDEX(Lists!$F:$F,MATCH(C6,Lists!$E:$E,0)),"Unmapped")) -> Metal
A7: By My Side | B7: Connor Price | C7: Hip-Hop/Rap | D7: Collin | E7: 1 - A Song you'd recommend any day | F7: 10 | G7: 8 | H7: =IF(N7="","",N7&IF(AND(MOD(N7,100)>=11,MOD(N7,100)<=13),"th",CHOOSE(MIN(5,MOD(N7,10)+1),"th","st","nd","rd","th"))) -> 6th | I7: Org Mgmt COE (1st League) | J7: =IFERROR(INDEX(Rounds!$A:$A,MATCH(I7,Rounds!$B:$B,0)),"ADD LEAGUE TO ROUNDS") -> 1 | K7: =IFERROR(VALUE(LEFT(E7,FIND(" - ",E7)-1)),"") -> 1 | L7: spotify:track:5FtOZv6MB6IWL2DneVYvoe | N7: =IF(F7="","",1+COUNTIFS($J:$J,J7,$K:$K,K7,$F:$F,">"&F7)+COUNTIFS($J:$J,J7,$K:$K,K7,$F:$F,F7,$G:$G,">"&G7)) -> 6 | O7: =IF(L7="","",SUMIFS(Votes!$E:$E,Votes!$A:$A,J7,Votes!$B:$B,K7,Votes!$D:$D,L7)) -> 10 | P7: =IF(L7="","",COUNTIFS(Votes!$A:$A,J7,Votes!$B:$B,K7,Votes!$D:$D,L7)) -> 8 | Q7: =IF(F7="","Unscored",IF(O7="","No URI",IF(AND(F7=0,O7=0),"Zero-vote",IF(AND(F7=O7,G7=P7),"OK",IF(AND(F7=0,O7>0,COUNTIFS(Votes!$A:$A,J7,Votes!$B:$B,K7,Votes!$C:$C,D7)=0),"Forfeited","Mismatch"))))) -> OK | R7: =MAX(IF(L7<>"",COUNTIF($L:$L,L7),0),COUNTIFS($A:$A,A7,$B:$B,B7)) -> 1 | S7: =IF(R7>1,COUNTIF($R$2:R7,">1"),"") | T7: =IF(L7="","",J7&"|"&K7&"|"&L7) -> 1|1|spotify:track:5FtOZv6MB6IWL2DneVYvoe | U7: =IF(C7="","",IFERROR(INDEX(Lists!$F:$F,MATCH(C7,Lists!$E:$E,0)),"Unmapped")) -> Hip-Hop/Rap
A8: Tous les mêmes | B8: Stromae | C8: Electronic/Pop | D8: Matt | E8: 1 - A Song you'd recommend any day | F8: 9 | G8: 6 | H8: =IF(N8="","",N8&IF(AND(MOD(N8,100)>=11,MOD(N8,100)<=13),"th",CHOOSE(MIN(5,MOD(N8,10)+1),"th","st","nd","rd","th"))) -> 7th | I8: Org Mgmt COE (1st League) | J8: =IFERROR(INDEX(Rounds!$A:$A,MATCH(I8,Rounds!$B:$B,0)),"ADD LEAGUE TO ROUNDS") -> 1 | K8: =IFERROR(VALUE(LEFT(E8,FIND(" - ",E8)-1)),"") -> 1 | L8: spotify:track:1GC1MIaRMW3kfVK9VyD5Ii | N8: =IF(F8="","",1+COUNTIFS($J:$J,J8,$K:$K,K8,$F:$F,">"&F8)+COUNTIFS($J:$J,J8,$K:$K,K8,$F:$F,F8,$G:$G,">"&G8)) -> 7 | O8: =IF(L8="","",SUMIFS(Votes!$E:$E,Votes!$A:$A,J8,Votes!$B:$B,K8,Votes!$D:$D,L8)) -> 9 | P8: =IF(L8="","",COUNTIFS(Votes!$A:$A,J8,Votes!$B:$B,K8,Votes!$D:$D,L8)) -> 6 | Q8: =IF(F8="","Unscored",IF(O8="","No URI",IF(AND(F8=0,O8=0),"Zero-vote",IF(AND(F8=O8,G8=P8),"OK",IF(AND(F8=0,O8>0,COUNTIFS(Votes!$A:$A,J8,Votes!$B:$B,K8,Votes!$C:$C,D8)=0),"Forfeited","Mismatch"))))) -> OK | R8: =MAX(IF(L8<>"",COUNTIF($L:$L,L8),0),COUNTIFS($A:$A,A8,$B:$B,B8)) -> 1 | S8: =IF(R8>1,COUNTIF($R$2:R8,">1"),"") | T8: =IF(L8="","",J8&"|"&K8&"|"&L8) -> 1|1|spotify:track:1GC1MIaRMW3kfVK9VyD5Ii | U8: =IF(C8="","",IFERROR(INDEX(Lists!$F:$F,MATCH(C8,Lists!$E:$E,0)),"Unmapped")) -> Electronic/Dance
A9: Granite | B9: Sleep Token | C9: Metal | D9: Leah | E9: 1 - A Song you'd recommend any day | F9: 8 | G9: 5 | H9: =IF(N9="","",N9&IF(AND(MOD(N9,100)>=11,MOD(N9,100)<=13),"th",CHOOSE(MIN(5,MOD(N9,10)+1),"th","st","nd","rd","th"))) -> 8th | I9: Org Mgmt COE (1st League) | J9: =IFERROR(INDEX(Rounds!$A:$A,MATCH(I9,Rounds!$B:$B,0)),"ADD LEAGUE TO ROUNDS") -> 1 | K9: =IFERROR(VALUE(LEFT(E9,FIND(" - ",E9)-1)),"") -> 1 | L9: spotify:track:4mxiv6HQfhqgIuN5iOONQd | N9: =IF(F9="","",1+COUNTIFS($J:$J,J9,$K:$K,K9,$F:$F,">"&F9)+COUNTIFS($J:$J,J9,$K:$K,K9,$F:$F,F9,$G:$G,">"&G9)) -> 8 | O9: =IF(L9="","",SUMIFS(Votes!$E:$E,Votes!$A:$A,J9,Votes!$B:$B,K9,Votes!$D:$D,L9)) -> 8 | P9: =IF(L9="","",COUNTIFS(Votes!$A:$A,J9,Votes!$B:$B,K9,Votes!$D:$D,L9)) -> 5 | Q9: =IF(F9="","Unscored",IF(O9="","No URI",IF(AND(F9=0,O9=0),"Zero-vote",IF(AND(F9=O9,G9=P9),"OK",IF(AND(F9=0,O9>0,COUNTIFS(Votes!$A:$A,J9,Votes!$B:$B,K9,Votes!$C:$C,D9)=0),"Forfeited","Mismatch"))))) -> OK | R9: =MAX(IF(L9<>"",COUNTIF($L:$L,L9),0),COUNTIFS($A:$A,A9,$B:$B,B9)) -> 1 | S9: =IF(R9>1,COUNTIF($R$2:R9,">1"),"") | T9: =IF(L9="","",J9&"|"&K9&"|"&L9) -> 1|1|spotify:track:4mxiv6HQfhqgIuN5iOONQd | U9: =IF(C9="","",IFERROR(INDEX(Lists!$F:$F,MATCH(C9,Lists!$E:$E,0)),"Unmapped")) -> Metal
A10: Unwritten | B10: Natasha Bedingfield | C10: Pop | D10: Olivia | E10: 1 - A Song you'd recommend any day | F10: 8 | G10: 5 | H10: =IF(N10="","",N10&IF(AND(MOD(N10,100)>=11,MOD(N10,100)<=13),"th",CHOOSE(MIN(5,MOD(N10,10)+1),"th","st","nd","rd","th"))) -> 8th | I10: Org Mgmt COE (1st League) | J10: =IFERROR(INDEX(Rounds!$A:$A,MATCH(I10,Rounds!$B:$B,0)),"ADD LEAGUE TO ROUNDS") -> 1 | K10: =IFERROR(VALUE(LEFT(E10,FIND(" - ",E10)-1)),"") -> 1 | L10: spotify:track:3U5JVgI2x4rDyHGObzJfNf | N10: =IF(F10="","",1+COUNTIFS($J:$J,J10,$K:$K,K10,$F:$F,">"&F10)+COUNTIFS($J:$J,J10,$K:$K,K10,$F:$F,F10,$G:$G,">"&G10)) -> 8 | O10: =IF(L10="","",SUMIFS(Votes!$E:$E,Votes!$A:$A,J10,Votes!$B:$B,K10,Votes!$D:$D,L10)) -> 8 | P10: =IF(L10="","",COUNTIFS(Votes!$A:$A,J10,Votes!$B:$B,K10,Votes!$D:$D,L10)) -> 5 | Q10: =IF(F10="","Unscored",IF(O10="","No URI",IF(AND(F10=0,O10=0),"Zero-vote",IF(AND(F10=O10,G10=P10),"OK",IF(AND(F10=0,O10>0,COUNTIFS(Votes!$A:$A,J10,Votes!$B:$B,K10,Votes!$C:$C,D10)=0),"Forfeited","Mismatch"))))) -> OK | R10: =MAX(IF(L10<>"",COUNTIF($L:$L,L10),0),COUNTIFS($A:$A,A10,$B:$B,B10)) -> 1 | S10: =IF(R10>1,COUNTIF($R$2:R10,">1"),"") | T10: =IF(L10="","",J10&"|"&K10&"|"&L10) -> 1|1|spotify:track:3U5JVgI2x4rDyHGObzJfNf | U10: =IF(C10="","",IFERROR(INDEX(Lists!$F:$F,MATCH(C10,Lists!$E:$E,0)),"Unmapped")) -> Pop
A11: Moon River | B11: Audrey Hepburn | C11: Jazz/Vocal | D11: Logan | E11: 1 - A Song you'd recommend any day | F11: 4 | G11: 4 | H11: =IF(N11="","",N11&IF(AND(MOD(N11,100)>=11,MOD(N11,100)<=13),"th",CHOOSE(MIN(5,MOD(N11,10)+1),"th","st","nd","rd","th"))) -> 10th | I11: Org Mgmt COE (1st League) | J11: =IFERROR(INDEX(Rounds!$A:$A,MATCH(I11,Rounds!$B:$B,0)),"ADD LEAGUE TO ROUNDS") -> 1 | K11: =IFERROR(VALUE(LEFT(E11,FIND(" - ",E11)-1)),"") -> 1 | L11: spotify:track:1XwAKjAZ1xDZOcuyZoqce4 | N11: =IF(F11="","",1+COUNTIFS($J:$J,J11,$K:$K,K11,$F:$F,">"&F11)+COUNTIFS($J:$J,J11,$K:$K,K11,$F:$F,F11,$G:$G,">"&G11)) -> 10 | O11: =IF(L11="","",SUMIFS(Votes!$E:$E,Votes!$A:$A,J11,Votes!$B:$B,K11,Votes!$D:$D,L11)) -> 4 | P11: =IF(L11="","",COUNTIFS(Votes!$A:$A,J11,Votes!$B:$B,K11,Votes!$D:$D,L11)) -> 4 | Q11: =IF(F11="","Unscored",IF(O11="","No URI",IF(AND(F11=0,O11=0),"Zero-vote",IF(AND(F11=O11,G11=P11),"OK",IF(AND(F11=0,O11>0,COUNTIFS(Votes!$A:$A,J11,Votes!$B:$B,K11,Votes!$C:$C,D11)=0),"Forfeited","Mismatch"))))) -> OK | R11: =MAX(IF(L11<>"",COUNTIF($L:$L,L11),0),COUNTIFS($A:$A,A11,$B:$B,B11)) -> 1 | S11: =IF(R11>1,COUNTIF($R$2:R11,">1"),"") | T11: =IF(L11="","",J11&"|"&K11&"|"&L11) -> 1|1|spotify:track:1XwAKjAZ1xDZOcuyZoqce4 | U11: =IF(C11="","",IFERROR(INDEX(Lists!$F:$F,MATCH(C11,Lists!$E:$E,0)),"Unmapped")) -> Jazz/Vocal
A12: At the Beginning | B12: Hollywood Sound Stars | C12: Soundtrack/Musical | D12: Maryann | E12: 1 - A Song you'd recommend any day | F12: 4 | G12: 3 | H12: =IF(N12="","",N12&IF(AND(MOD(N12,100)>=11,MOD(N12,100)<=13),"th",CHOOSE(MIN(5,MOD(N12,10)+1),"th","st","nd","rd","th"))) -> 11th | I12: Org Mgmt COE (1st League) | J12: =IFERROR(INDEX(Rounds!$A:$A,MATCH(I12,Rounds!$B:$B,0)),"ADD LEAGUE TO ROUNDS") -> 1 | K12: =IFERROR(VALUE(LEFT(E12,FIND(" - ",E12)-1)),"") -> 1 | L12: spotify:track:5Qn0AlYJHOKogfbE36or9V | N12: =IF(F12="","",1+COUNTIFS($J:$J,J12,$K:$K,K12,$F:$F,">"&F12)+COUNTIFS($J:$J,J12,$K:$K,K12,$F:$F,F12,$G:$G,">"&G12)) -> 11 | O12: =IF(L12="","",SUMIFS(Votes!$E:$E,Votes!$A:$A,J12,Votes!$B:$B,K12,Votes!$D:$D,L12)) -> 4 | P12: =IF(L12="","",COUNTIFS(Votes!$A:$A,J12,Votes!$B:$B,K12,Votes!$D:$D,L12)) -> 3 | Q12: =IF(F12="","Unscored",IF(O12="","No URI",IF(AND(F12=0,O12=0),"Zero-vote",IF(AND(F12=O12,G12=P12),"OK",IF(AND(F12=0,O12>0,COUNTIFS(Votes!$A:$A,J12,Votes!$B:$B,K12,Votes!$C:$C,D12)=0),"Forfeited","Mismatch"))))) -> OK | R12: =MAX(IF(L12<>"",COUNTIF($L:$L,L12),0),COUNTIFS($A:$A,A12,$B:$B,B12)) -> 1 | S12: =IF(R12>1,COUNTIF($R$2:R12,">1"),"") | T12: =IF(L12="","",J12&"|"&K12&"|"&L12) -> 1|1|spotify:track:5Qn0AlYJHOKogfbE36or9V | U12: =IF(C12="","",IFERROR(INDEX(Lists!$F:$F,MATCH(C12,Lists!$E:$E,0)),"Unmapped")) -> Soundtrack/Musical
A13: The Ballad of the Witches' Road | B13: Kathryn Hahn | C13: Soundtrack/Musical | D13: Merita | E13: 2 - Halloween-ish Songs | F13: 16 | G13: 7 | H13: =IF(N13="","",N13&IF(AND(MOD(N13,100)>=11,MOD(N13,100)<=13),"th",CHOOSE(MIN(5,MOD(N13,10)+1),"th","st","nd","rd","th"))) -> 1st | I13: Org Mgmt COE (1st League) | J13: =IFERROR(INDEX(Rounds!$A:$A,MATCH(I13,Rounds!$B:$B,0)),"ADD LEAGUE TO ROUNDS") -> 1 | K13: =IFERROR(VALUE(LEFT(E13,FIND(" - ",E13)-1)),"") -> 2 | L13: spotify:track:59h6Uw3m5ClwHnEcKXh8hg | N13: =IF(F13="","",1+COUNTIFS($J:$J,J13,$K:$K,K13,$F:$F,">"&F13)+COUNTIFS($J:$J,J13,$K:$K,K13,$F:$F,F13,$G:$G,">"&G13)) -> 1 | O13: =IF(L13="","",SUMIFS(Votes!$E:$E,Votes!$A:$A,J13,Votes!$B:$B,K13,Votes!$D:$D,L13)) -> 16 | P13: =IF(L13="","",COUNTIFS(Votes!$A:$A,J13,Votes!$B:$B,K13,Votes!$D:$D,L13)) -> 7 | Q13: =IF(F13="","Unscored",IF(O13="","No URI",IF(AND(F13=0,O13=0),"Zero-vote",IF(AND(F13=O13,G13=P13),"OK",IF(AND(F13=0,O13>0,COUNTIFS(Votes!$A:$A,J13,Votes!$B:$B,K13,Votes!$C:$C,D13)=0),"Forfeited","Mismatch"))))) -> OK | R13: =MAX(IF(L13<>"",COUNTIF($L:$L,L13),0),COUNTIFS($A:$A,A13,$B:$B,B13)) -> 1 | S13: =IF(R13>1,COUNTIF($R$2:R13,">1"),"") | T13: =IF(L13="","",J13&"|"&K13&"|"&L13) -> 1|2|spotify:track:59h6Uw3m5ClwHnEcKXh8hg | U13: =IF(C13="","",IFERROR(INDEX(Lists!$F:$F,MATCH(C13,Lists!$E:$E,0)),"Unmapped")) -> Soundtrack/Musical
... A787: Crawling in the Dark | B787: Hoobastank | C787: Rock | D787: Colleen | E787: 8 - After Hours | F787: 6 | G787: 5 | H787: =IF(N787="","",N787&IF(AND(MOD(N787,100)>=11,MOD(N787,100)<=13),"th",CHOOSE(MIN(5,MOD(N787,10)+1),"th","st","nd","rd","th"))) -> 14th | I787: Lucky Number 7 (7th League) | J787: =IFERROR(INDEX(Rounds!$A:$A,MATCH(I787,Rounds!$B:$B,0)),"ADD LEAGUE TO ROUNDS") -> 7 | K787: =IFERROR(VALUE(LEFT(E787,FIND(" - ",E787)-1)),"") -> 8 | L787: spotify:track:1PJRDeZSoZk7gtisdTYfLi | N787: =IF(F787="","",1+COUNTIFS($J:$J,J787,$K:$K,K787,$F:$F,">"&F787)+COUNTIFS($J:$J,J787,$K:$K,K787,$F:$F,F787,$G:$G,">"&G787)) -> 14 | O787: =IF(L787="","",SUMIFS(Votes!$E:$E,Votes!$A:$A,J787,Votes!$B:$B,K787,Votes!$D:$D,L787)) -> 6 | P787: =IF(L787="","",COUNTIFS(Votes!$A:$A,J787,Votes!$B:$B,K787,Votes!$D:$D,L787)) -> 5 | Q787: =IF(F787="","Unscored",IF(O787="","No URI",IF(AND(F787=0,O787=0),"Zero-vote",IF(AND(F787=O787,G787=P787),"OK",IF(AND(F787=0,O787>0,COUNTIFS(Votes!$A:$A,J787,Votes!$B:$B,K787,Votes!$C:$C,D787)=0),"Forfeited","Mismatch"))))) -> OK | R787: =MAX(IF(L787<>"",COUNTIF($L:$L,L787),0),COUNTIFS($A:$A,A787,$B:$B,B787)) -> 1 | S787: =IF(R787>1,COUNTIF($R$2:R787,">1"),"") | T787: =IF(L787="","",J787&"|"&K787&"|"&L787) -> 7|8|spotify:track:1PJRDeZSoZk7gtisdTYfLi | U787: =IF(C787="","",IFERROR(INDEX(Lists!$F:$F,MATCH(C787,Lists!$E:$E,0)),"Unmapped")) -> Rock
A788: This Is America | B788: Childish Gambino | C788: Hip-Hop/Rap | E788: 1 - First Impressions | H788: =IF(N788="","",N788&IF(AND(MOD(N788,100)>=11,MOD(N788,100)<=13),"th",CHOOSE(MIN(5,MOD(N788,10)+1),"th","st","nd","rd","th"))) | I788: The Soundtrack of Us (8th League) | J788: =IFERROR(INDEX(Rounds!$A:$A,MATCH(I788,Rounds!$B:$B,0)),"ADD LEAGUE TO ROUNDS") -> 8 | K788: =IFERROR(VALUE(LEFT(E788,FIND(" - ",E788)-1)),"") -> 1 | N788: =IF(F788="","",1+COUNTIFS($J:$J,J788,$K:$K,K788,$F:$F,">"&F788)+COUNTIFS($J:$J,J788,$K:$K,K788,$F:$F,F788,$G:$G,">"&G788)) | O788: =IF(L788="","",SUMIFS(Votes!$E:$E,Votes!$A:$A,J788,Votes!$B:$B,K788,Votes!$D:$D,L788)) | P788: =IF(L788="","",COUNTIFS(Votes!$A:$A,J788,Votes!$B:$B,K788,Votes!$D:$D,L788)) | Q788: =IF(F788="","Unscored",IF(O788="","No URI",IF(AND(F788=0,O788=0),"Zero-vote",IF(AND(F788=O788,G788=P788),"OK",IF(AND(F788=0,O788>0,COUNTIFS(Votes!$A:$A,J788,Votes!$B:$B,K788,Votes!$C:$C,D788)=0),"Forfeited","Mismatch"))))) -> Unscored | R788: =MAX(IF(L788<>"",COUNTIF($L:$L,L788),0),COUNTIFS($A:$A,A788,$B:$B,B788)) -> 1 | S788: =IF(R788>1,COUNTIF($R$2:R788,">1"),"") | T788: =IF(L788="","",J788&"|"&K788&"|"&L788) | U788: =IF(C788="","",IFERROR(INDEX(Lists!$F:$F,MATCH(C788,Lists!$E:$E,0)),"Unmapped")) -> Hip-Hop/Rap
A789: Ms. Jackson | B789: Outkast | C789: Hip-Hop/Rap | E789: 1 - First Impressions | H789: =IF(N789="","",N789&IF(AND(MOD(N789,100)>=11,MOD(N789,100)<=13),"th",CHOOSE(MIN(5,MOD(N789,10)+1),"th","st","nd","rd","th"))) | I789: The Soundtrack of Us (8th League) | J789: =IFERROR(INDEX(Rounds!$A:$A,MATCH(I789,Rounds!$B:$B,0)),"ADD LEAGUE TO ROUNDS") -> 8 | K789: =IFERROR(VALUE(LEFT(E789,FIND(" - ",E789)-1)),"") -> 1 | N789: =IF(F789="","",1+COUNTIFS($J:$J,J789,$K:$K,K789,$F:$F,">"&F789)+COUNTIFS($J:$J,J789,$K:$K,K789,$F:$F,F789,$G:$G,">"&G789)) | O789: =IF(L789="","",SUMIFS(Votes!$E:$E,Votes!$A:$A,J789,Votes!$B:$B,K789,Votes!$D:$D,L789)) | P789: =IF(L789="","",COUNTIFS(Votes!$A:$A,J789,Votes!$B:$B,K789,Votes!$D:$D,L789)) | Q789: =IF(F789="","Unscored",IF(O789="","No URI",IF(AND(F789=0,O789=0),"Zero-vote",IF(AND(F789=O789,G789=P789),"OK",IF(AND(F789=0,O789>0,COUNTIFS(Votes!$A:$A,J789,Votes!$B:$B,K789,Votes!$C:$C,D789)=0),"Forfeited","Mismatch"))))) -> Unscored | R789: =MAX(IF(L789<>"",COUNTIF($L:$L,L789),0),COUNTIFS($A:$A,A789,$B:$B,B789)) -> 1 | S789: =IF(R789>1,COUNTIF($R$2:R789,">1"),"") | T789: =IF(L789="","",J789&"|"&K789&"|"&L789) | U789: =IF(C789="","",IFERROR(INDEX(Lists!$F:$F,MATCH(C789,Lists!$E:$E,0)),"Unmapped")) -> Hip-Hop/Rap
A790: Dear Maria, Count Me In | B790: All Time Low | C790: Rock | E790: 1 - First Impressions | H790: =IF(N790="","",N790&IF(AND(MOD(N790,100)>=11,MOD(N790,100)<=13),"th",CHOOSE(MIN(5,MOD(N790,10)+1),"th","st","nd","rd","th"))) | I790: The Soundtrack of Us (8th League) | J790: =IFERROR(INDEX(Rounds!$A:$A,MATCH(I790,Rounds!$B:$B,0)),"ADD LEAGUE TO ROUNDS") -> 8 | K790: =IFERROR(VALUE(LEFT(E790,FIND(" - ",E790)-1)),"") -> 1 | N790: =IF(F790="","",1+COUNTIFS($J:$J,J790,$K:$K,K790,$F:$F,">"&F790)+COUNTIFS($J:$J,J790,$K:$K,K790,$F:$F,F790,$G:$G,">"&G790)) | O790: =IF(L790="","",SUMIFS(Votes!$E:$E,Votes!$A:$A,J790,Votes!$B:$B,K790,Votes!$D:$D,L790)) | P790: =IF(L790="","",COUNTIFS(Votes!$A:$A,J790,Votes!$B:$B,K790,Votes!$D:$D,L790)) | Q790: =IF(F790="","Unscored",IF(O790="","No URI",IF(AND(F790=0,O790=0),"Zero-vote",IF(AND(F790=O790,G790=P790),"OK",IF(AND(F790=0,O790>0,COUNTIFS(Votes!$A:$A,J790,Votes!$B:$B,K790,Votes!$C:$C,D790)=0),"Forfeited","Mismatch"))))) -> Unscored | R790: =MAX(IF(L790<>"",COUNTIF($L:$L,L790),0),COUNTIFS($A:$A,A790,$B:$B,B790)) -> 1 | S790: =IF(R790>1,COUNTIF($R$2:R790,">1"),"") | T790: =IF(L790="","",J790&"|"&K790&"|"&L790) | U790: =IF(C790="","",IFERROR(INDEX(Lists!$F:$F,MATCH(C790,Lists!$E:$E,0)),"Unmapped")) -> Rock
A791: You Give Love A Bad Name | B791: Bon Jovi | C791: Rock | E791: 1 - First Impressions | H791: =IF(N791="","",N791&IF(AND(MOD(N791,100)>=11,MOD(N791,100)<=13),"th",CHOOSE(MIN(5,MOD(N791,10)+1),"th","st","nd","rd","th"))) | I791: The Soundtrack of Us (8th League) | J791: =IFERROR(INDEX(Rounds!$A:$A,MATCH(I791,Rounds!$B:$B,0)),"ADD LEAGUE TO ROUNDS") -> 8 | K791: =IFERROR(VALUE(LEFT(E791,FIND(" - ",E791)-1)),"") -> 1 | N791: =IF(F791="","",1+COUNTIFS($J:$J,J791,$K:$K,K791,$F:$F,">"&F791)+COUNTIFS($J:$J,J791,$K:$K,K791,$F:$F,F791,$G:$G,">"&G791)) | O791: =IF(L791="","",SUMIFS(Votes!$E:$E,Votes!$A:$A,J791,Votes!$B:$B,K791,Votes!$D:$D,L791)) | P791: =IF(L791="","",COUNTIFS(Votes!$A:$A,J791,Votes!$B:$B,K791,Votes!$D:$D,L791)) | Q791: =IF(F791="","Unscored",IF(O791="","No URI",IF(AND(F791=0,O791=0),"Zero-vote",IF(AND(F791=O791,G791=P791),"OK",IF(AND(F791=0,O791>0,COUNTIFS(Votes!$A:$A,J791,Votes!$B:$B,K791,Votes!$C:$C,D791)=0),"Forfeited","Mismatch"))))) -> Unscored | R791: =MAX(IF(L791<>"",COUNTIF($L:$L,L791),0),COUNTIFS($A:$A,A791,$B:$B,B791)) -> 1 | S791: =IF(R791>1,COUNTIF($R$2:R791,">1"),"") | T791: =IF(L791="","",J791&"|"&K791&"|"&L791) | U791: =IF(C791="","",IFERROR(INDEX(Lists!$F:$F,MATCH(C791,Lists!$E:$E,0)),"Unmapped")) -> Rock
A792: Fuel | B792: Metallica | C792: Metal | E792: 1 - First Impressions | H792: =IF(N792="","",N792&IF(AND(MOD(N792,100)>=11,MOD(N792,100)<=13),"th",CHOOSE(MIN(5,MOD(N792,10)+1),"th","st","nd","rd","th"))) | I792: The Soundtrack of Us (8th League) | J792: =IFERROR(INDEX(Rounds!$A:$A,MATCH(I792,Rounds!$B:$B,0)),"ADD LEAGUE TO ROUNDS") -> 8 | K792: =IFERROR(VALUE(LEFT(E792,FIND(" - ",E792)-1)),"") -> 1 | N792: =IF(F792="","",1+COUNTIFS($J:$J,J792,$K:$K,K792,$F:$F,">"&F792)+COUNTIFS($J:$J,J792,$K:$K,K792,$F:$F,F792,$G:$G,">"&G792)) | O792: =IF(L792="","",SUMIFS(Votes!$E:$E,Votes!$A:$A,J792,Votes!$B:$B,K792,Votes!$D:$D,L792)) | P792: =IF(L792="","",COUNTIFS(Votes!$A:$A,J792,Votes!$B:$B,K792,Votes!$D:$D,L792)) | Q792: =IF(F792="","Unscored",IF(O792="","No URI",IF(AND(F792=0,O792=0),"Zero-vote",IF(AND(F792=O792,G792=P792),"OK",IF(AND(F792=0,O792>0,COUNTIFS(Votes!$A:$A,J792,Votes!$B:$B,K792,Votes!$C:$C,D792)=0),"Forfeited","Mismatch"))))) -> Unscored | R792: =MAX(IF(L792<>"",COUNTIF($L:$L,L792),0),COUNTIFS($A:$A,A792,$B:$B,B792)) -> 1 | S792: =IF(R792>1,COUNTIF($R$2:R792,">1"),"") | T792: =IF(L792="","",J792&"|"&K792&"|"&L792) | U792: =IF(C792="","",IFERROR(INDEX(Lists!$F:$F,MATCH(C792,Lists!$E:$E,0)),"Unmapped")) -> Metal
A793: Royals | B793: Lorde | C793: Pop | E793: 1 - First Impressions | H793: =IF(N793="","",N793&IF(AND(MOD(N793,100)>=11,MOD(N793,100)<=13),"th",CHOOSE(MIN(5,MOD(N793,10)+1),"th","st","nd","rd","th"))) | I793: The Soundtrack of Us (8th League) | J793: =IFERROR(INDEX(Rounds!$A:$A,MATCH(I793,Rounds!$B:$B,0)),"ADD LEAGUE TO ROUNDS") -> 8 | K793: =IFERROR(VALUE(LEFT(E793,FIND(" - ",E793)-1)),"") -> 1 | N793: =IF(F793="","",1+COUNTIFS($J:$J,J793,$K:$K,K793,$F:$F,">"&F793)+COUNTIFS($J:$J,J793,$K:$K,K793,$F:$F,F793,$G:$G,">"&G793)) | O793: =IF(L793="","",SUMIFS(Votes!$E:$E,Votes!$A:$A,J793,Votes!$B:$B,K793,Votes!$D:$D,L793)) | P793: =IF(L793="","",COUNTIFS(Votes!$A:$A,J793,Votes!$B:$B,K793,Votes!$D:$D,L793)) | Q793: =IF(F793="","Unscored",IF(O793="","No URI",IF(AND(F793=0,O793=0),"Zero-vote",IF(AND(F793=O793,G793=P793),"OK",IF(AND(F793=0,O793>0,COUNTIFS(Votes!$A:$A,J793,Votes!$B:$B,K793,Votes!$C:$C,D793)=0),"Forfeited","Mismatch"))))) -> Unscored | R793: =MAX(IF(L793<>"",COUNTIF($L:$L,L793),0),COUNTIFS($A:$A,A793,$B:$B,B793)) -> 1 | S793: =IF(R793>1,COUNTIF($R$2:R793,">1"),"") | T793: =IF(L793="","",J793&"|"&K793&"|"&L793) | U793: =IF(C793="","",IFERROR(INDEX(Lists!$F:$F,MATCH(C793,Lists!$E:$E,0)),"Unmapped")) -> Pop
A794: 7563 | B794: Florence Road | C794: Pop | E794: 1 - First Impressions | H794: =IF(N794="","",N794&IF(AND(MOD(N794,100)>=11,MOD(N794,100)<=13),"th",CHOOSE(MIN(5,MOD(N794,10)+1),"th","st","nd","rd","th"))) | I794: The Soundtrack of Us (8th League) | J794: =IFERROR(INDEX(Rounds!$A:$A,MATCH(I794,Rounds!$B:$B,0)),"ADD LEAGUE TO ROUNDS") -> 8 | K794: =IFERROR(VALUE(LEFT(E794,FIND(" - ",E794)-1)),"") -> 1 | N794: =IF(F794="","",1+COUNTIFS($J:$J,J794,$K:$K,K794,$F:$F,">"&F794)+COUNTIFS($J:$J,J794,$K:$K,K794,$F:$F,F794,$G:$G,">"&G794)) | O794: =IF(L794="","",SUMIFS(Votes!$E:$E,Votes!$A:$A,J794,Votes!$B:$B,K794,Votes!$D:$D,L794)) | P794: =IF(L794="","",COUNTIFS(Votes!$A:$A,J794,Votes!$B:$B,K794,Votes!$D:$D,L794)) | Q794: =IF(F794="","Unscored",IF(O794="","No URI",IF(AND(F794=0,O794=0),"Zero-vote",IF(AND(F794=O794,G794=P794),"OK",IF(AND(F794=0,O794>0,COUNTIFS(Votes!$A:$A,J794,Votes!$B:$B,K794,Votes!$C:$C,D794)=0),"Forfeited","Mismatch"))))) -> Unscored | R794: =MAX(IF(L794<>"",COUNTIF($L:$L,L794),0),COUNTIFS($A:$A,A794,$B:$B,B794)) -> 1 | S794: =IF(R794>1,COUNTIF($R$2:R794,">1"),"") | T794: =IF(L794="","",J794&"|"&K794&"|"&L794) | U794: =IF(C794="","",IFERROR(INDEX(Lists!$F:$F,MATCH(C794,Lists!$E:$E,0)),"Unmapped")) -> Pop
A795: We R Who We R | B795: Kesha | C795: Pop | E795: 1 - First Impressions | H795: =IF(N795="","",N795&IF(AND(MOD(N795,100)>=11,MOD(N795,100)<=13),"th",CHOOSE(MIN(5,MOD(N795,10)+1),"th","st","nd","rd","th"))) | I795: The Soundtrack of Us (8th League) | J795: =IFERROR(INDEX(Rounds!$A:$A,MATCH(I795,Rounds!$B:$B,0)),"ADD LEAGUE TO ROUNDS") -> 8 | K795: =IFERROR(VALUE(LEFT(E795,FIND(" - ",E795)-1)),"") -> 1 | N795: =IF(F795="","",1+COUNTIFS($J:$J,J795,$K:$K,K795,$F:$F,">"&F795)+COUNTIFS($J:$J,J795,$K:$K,K795,$F:$F,F795,$G:$G,">"&G795)) | O795: =IF(L795="","",SUMIFS(Votes!$E:$E,Votes!$A:$A,J795,Votes!$B:$B,K795,Votes!$D:$D,L795)) | P795: =IF(L795="","",COUNTIFS(Votes!$A:$A,J795,Votes!$B:$B,K795,Votes!$D:$D,L795)) | Q795: =IF(F795="","Unscored",IF(O795="","No URI",IF(AND(F795=0,O795=0),"Zero-vote",IF(AND(F795=O795,G795=P795),"OK",IF(AND(F795=0,O795>0,COUNTIFS(Votes!$A:$A,J795,Votes!$B:$B,K795,Votes!$C:$C,D795)=0),"Forfeited","Mismatch"))))) -> Unscored | R795: =MAX(IF(L795<>"",COUNTIF($L:$L,L795),0),COUNTIFS($A:$A,A795,$B:$B,B795)) -> 1 | S795: =IF(R795>1,COUNTIF($R$2:R795,">1"),"") | T795: =IF(L795="","",J795&"|"&K795&"|"&L795) | U795: =IF(C795="","",IFERROR(INDEX(Lists!$F:$F,MATCH(C795,Lists!$E:$E,0)),"Unmapped")) -> Pop
A796: Nothing Compares 2 U | B796: Sinead O'Connor | C796: Rock | E796: 1 - First Impressions | H796: =IF(N796="","",N796&IF(AND(MOD(N796,100)>=11,MOD(N796,100)<=13),"th",CHOOSE(MIN(5,MOD(N796,10)+1),"th","st","nd","rd","th"))) | I796: The Soundtrack of Us (8th League) | J796: =IFERROR(INDEX(Rounds!$A:$A,MATCH(I796,Rounds!$B:$B,0)),"ADD LEAGUE TO ROUNDS") -> 8 | K796: =IFERROR(VALUE(LEFT(E796,FIND(" - ",E796)-1)),"") -> 1 | N796: =IF(F796="","",1+COUNTIFS($J:$J,J796,$K:$K,K796,$F:$F,">"&F796)+COUNTIFS($J:$J,J796,$K:$K,K796,$F:$F,F796,$G:$G,">"&G796)) | O796: =IF(L796="","",SUMIFS(Votes!$E:$E,Votes!$A:$A,J796,Votes!$B:$B,K796,Votes!$D:$D,L796)) | P796: =IF(L796="","",COUNTIFS(Votes!$A:$A,J796,Votes!$B:$B,K796,Votes!$D:$D,L796)) | Q796: =IF(F796="","Unscored",IF(O796="","No URI",IF(AND(F796=0,O796=0),"Zero-vote",IF(AND(F796=O796,G796=P796),"OK",IF(AND(F796=0,O796>0,COUNTIFS(Votes!$A:$A,J796,Votes!$B:$B,K796,Votes!$C:$C,D796)=0),"Forfeited","Mismatch"))))) -> Unscored | R796: =MAX(IF(L796<>"",COUNTIF($L:$L,L796),0),COUNTIFS($A:$A,A796,$B:$B,B796)) -> 1 | S796: =IF(R796>1,COUNTIF($R$2:R796,">1"),"") | T796: =IF(L796="","",J796&"|"&K796&"|"&L796) | U796: =IF(C796="","",IFERROR(INDEX(Lists!$F:$F,MATCH(C796,Lists!$E:$E,0)),"Unmapped")) -> Rock
A797: Hypotheticals | B797: Lake Street Dive | C797: R&B/Soul | E797: 1 - First Impressions | H797: =IF(N797="","",N797&IF(AND(MOD(N797,100)>=11,MOD(N797,100)<=13),"th",CHOOSE(MIN(5,MOD(N797,10)+1),"th","st","nd","rd","th"))) | I797: The Soundtrack of Us (8th League) | J797: =IFERROR(INDEX(Rounds!$A:$A,MATCH(I797,Rounds!$B:$B,0)),"ADD LEAGUE TO ROUNDS") -> 8 | K797: =IFERROR(VALUE(LEFT(E797,FIND(" - ",E797)-1)),"") -> 1 | N797: =IF(F797="","",1+COUNTIFS($J:$J,J797,$K:$K,K797,$F:$F,">"&F797)+COUNTIFS($J:$J,J797,$K:$K,K797,$F:$F,F797,$G:$G,">"&G797)) | O797: =IF(L797="","",SUMIFS(Votes!$E:$E,Votes!$A:$A,J797,Votes!$B:$B,K797,Votes!$D:$D,L797)) | P797: =IF(L797="","",COUNTIFS(Votes!$A:$A,J797,Votes!$B:$B,K797,Votes!$D:$D,L797)) | Q797: =IF(F797="","Unscored",IF(O797="","No URI",IF(AND(F797=0,O797=0),"Zero-vote",IF(AND(F797=O797,G797=P797),"OK",IF(AND(F797=0,O797>0,COUNTIFS(Votes!$A:$A,J797,Votes!$B:$B,K797,Votes!$C:$C,D797)=0),"Forfeited","Mismatch"))))) -> Unscored | R797: =MAX(IF(L797<>"",COUNTIF($L:$L,L797),0),COUNTIFS($A:$A,A797,$B:$B,B797)) -> 1 | S797: =IF(R797>1,COUNTIF($R$2:R797,">1"),"") | T797: =IF(L797="","",J797&"|"&K797&"|"&L797) | U797: =IF(C797="","",IFERROR(INDEX(Lists!$F:$F,MATCH(C797,Lists!$E:$E,0)),"Unmapped")) -> R&B/Soul
A798: Don't Stop Believin' (2022 Remaster) | B798: Journey | C798: Rock | E798: 1 - First Impressions | H798: =IF(N798="","",N798&IF(AND(MOD(N798,100)>=11,MOD(N798,100)<=13),"th",CHOOSE(MIN(5,MOD(N798,10)+1),"th","st","nd","rd","th"))) | I798: The Soundtrack of Us (8th League) | J798: =IFERROR(INDEX(Rounds!$A:$A,MATCH(I798,Rounds!$B:$B,0)),"ADD LEAGUE TO ROUNDS") -> 8 | K798: =IFERROR(VALUE(LEFT(E798,FIND(" - ",E798)-1)),"") -> 1 | N798: =IF(F798="","",1+COUNTIFS($J:$J,J798,$K:$K,K798,$F:$F,">"&F798)+COUNTIFS($J:$J,J798,$K:$K,K798,$F:$F,F798,$G:$G,">"&G798)) | O798: =IF(L798="","",SUMIFS(Votes!$E:$E,Votes!$A:$A,J798,Votes!$B:$B,K798,Votes!$D:$D,L798)) | P798: =IF(L798="","",COUNTIFS(Votes!$A:$A,J798,Votes!$B:$B,K798,Votes!$D:$D,L798)) | Q798: =IF(F798="","Unscored",IF(O798="","No URI",IF(AND(F798=0,O798=0),"Zero-vote",IF(AND(F798=O798,G798=P798),"OK",IF(AND(F798=0,O798>0,COUNTIFS(Votes!$A:$A,J798,Votes!$B:$B,K798,Votes!$C:$C,D798)=0),"Forfeited","Mismatch"))))) -> Unscored | R798: =MAX(IF(L798<>"",COUNTIF($L:$L,L798),0),COUNTIFS($A:$A,A798,$B:$B,B798)) -> 1 | S798: =IF(R798>1,COUNTIF($R$2:R798,">1"),"") | T798: =IF(L798="","",J798&"|"&K798&"|"&L798) | U798: =IF(C798="","",IFERROR(INDEX(Lists!$F:$F,MATCH(C798,Lists!$E:$E,0)),"Unmapped")) -> Rock
A799: WOM | B799: Definitely Maybe | C799: Rock | E799: 1 - First Impressions | H799: =IF(N799="","",N799&IF(AND(MOD(N799,100)>=11,MOD(N799,100)<=13),"th",CHOOSE(MIN(5,MOD(N799,10)+1),"th","st","nd","rd","th"))) | I799: The Soundtrack of Us (8th League) | J799: =IFERROR(INDEX(Rounds!$A:$A,MATCH(I799,Rounds!$B:$B,0)),"ADD LEAGUE TO ROUNDS") -> 8 | K799: =IFERROR(VALUE(LEFT(E799,FIND(" - ",E799)-1)),"") -> 1 | N799: =IF(F799="","",1+COUNTIFS($J:$J,J799,$K:$K,K799,$F:$F,">"&F799)+COUNTIFS($J:$J,J799,$K:$K,K799,$F:$F,F799,$G:$G,">"&G799)) | O799: =IF(L799="","",SUMIFS(Votes!$E:$E,Votes!$A:$A,J799,Votes!$B:$B,K799,Votes!$D:$D,L799)) | P799: =IF(L799="","",COUNTIFS(Votes!$A:$A,J799,Votes!$B:$B,K799,Votes!$D:$D,L799)) | Q799: =IF(F799="","Unscored",IF(O799="","No URI",IF(AND(F799=0,O799=0),"Zero-vote",IF(AND(F799=O799,G799=P799),"OK",IF(AND(F799=0,O799>0,COUNTIFS(Votes!$A:$A,J799,Votes!$B:$B,K799,Votes!$C:$C,D799)=0),"Forfeited","Mismatch"))))) -> Unscored | R799: =MAX(IF(L799<>"",COUNTIF($L:$L,L799),0),COUNTIFS($A:$A,A799,$B:$B,B799)) -> 1 | S799: =IF(R799>1,COUNTIF($R$2:R799,">1"),"") | T799: =IF(L799="","",J799&"|"&K799&"|"&L799) | U799: =IF(C799="","",IFERROR(INDEX(Lists!$F:$F,MATCH(C799,Lists!$E:$E,0)),"Unmapped")) -> Rock
... A817: Blinded By The Light | B817: Manfred Mann's Earth Band | C817: Rock | E817: 2 - Wait…That's Not the Lyric? | H817: =IF(N817="","",N817&IF(AND(MOD(N817,100)>=11,MOD(N817,100)<=13),"th",CHOOSE(MIN(5,MOD(N817,10)+1),"th","st","nd","rd","th"))) | I817: The Soundtrack of Us (8th League) | J817: =IFERROR(INDEX(Rounds!$A:$A,MATCH(I817,Rounds!$B:$B,0)),"ADD LEAGUE TO ROUNDS") -> 8 | K817: =IFERROR(VALUE(LEFT(E817,FIND(" - ",E817)-1)),"") -> 2 | N817: =IF(F817="","",1+COUNTIFS($J:$J,J817,$K:$K,K817,$F:$F,">"&F817)+COUNTIFS($J:$J,J817,$K:$K,K817,$F:$F,F817,$G:$G,">"&G817)) | O817: =IF(L817="","",SUMIFS(Votes!$E:$E,Votes!$A:$A,J817,Votes!$B:$B,K817,Votes!$D:$D,L817)) | P817: =IF(L817="","",COUNTIFS(Votes!$A:$A,J817,Votes!$B:$B,K817,Votes!$D:$D,L817)) | Q817: =IF(F817="","Unscored",IF(O817="","No URI",IF(AND(F817=0,O817=0),"Zero-vote",IF(AND(F817=O817,G817=P817),"OK",IF(AND(F817=0,O817>0,COUNTIFS(Votes!$A:$A,J817,Votes!$B:$B,K817,Votes!$C:$C,D817)=0),"Forfeited","Mismatch"))))) -> Unscored | R817: =MAX(IF(L817<>"",COUNTIF($L:$L,L817),0),COUNTIFS($A:$A,A817,$B:$B,B817)) -> 1 | S817: =IF(R817>1,COUNTIF($R$2:R817,">1"),"") | T817: =IF(L817="","",J817&"|"&K817&"|"&L817) | U817: =IF(C817="","",IFERROR(INDEX(Lists!$F:$F,MATCH(C817,Lists!$E:$E,0)),"Unmapped")) -> Rock

Sheet Votes
A1: League # | B1: Round # | C1: Voter | D1: Spotify URI | E1: Points | F1: Match Row | G1: Song | H1: Artist | I1: Submitter | J1: Check | K1: Vote Key
A2: 1 | B2: 1 | C2: Collin | D2: spotify:track:3U5JVgI2x4rDyHGObzJfNf | E2: 2 | F2: =IFERROR(MATCH(A2&"|"&B2&"|"&D2,'All Song Rankings'!$T:$T,0),0) -> 10 | G2: =IF(F2=0,"NOT FOUND",INDEX('All Song Rankings'!$A:$A,F2)) -> Unwritten | H2: =IF(F2=0,"NOT FOUND",INDEX('All Song Rankings'!$B:$B,F2)) -> Natasha Bedingfield | I2: =IF(F2=0,"NOT FOUND",INDEX('All Song Rankings'!$D:$D,F2)) -> Olivia | J2: =IF(F2=0,"NOT FOUND",IF(C2=I2,"SELF-VOTE",IF(COUNTIF($K:$K,K2)>1,"DUPLICATE","OK"))) -> OK | K2: =A2&"|"&B2&"|"&C2&"|"&D2 -> 1|1|Collin|spotify:track:3U5JVgI2x4rDyHGObzJfNf
A3: 1 | B3: 1 | C3: Collin | D3: spotify:track:3hZIvVYZWsuFpdWdXQFgKx | E3: 5 | F3: =IFERROR(MATCH(A3&"|"&B3&"|"&D3,'All Song Rankings'!$T:$T,0),0) -> 6 | G3: =IF(F3=0,"NOT FOUND",INDEX('All Song Rankings'!$A:$A,F3)) -> Euclid | H3: =IF(F3=0,"NOT FOUND",INDEX('All Song Rankings'!$B:$B,F3)) -> Sleep Token | I3: =IF(F3=0,"NOT FOUND",INDEX('All Song Rankings'!$D:$D,F3)) -> Kristen | J3: =IF(F3=0,"NOT FOUND",IF(C3=I3,"SELF-VOTE",IF(COUNTIF($K:$K,K3)>1,"DUPLICATE","OK"))) -> OK | K3: =A3&"|"&B3&"|"&C3&"|"&D3 -> 1|1|Collin|spotify:track:3hZIvVYZWsuFpdWdXQFgKx
A4: 1 | B4: 1 | C4: Collin | D4: spotify:track:4kbj5MwxO1bq9wjT5g9HaA | E4: 1 | F4: =IFERROR(MATCH(A4&"|"&B4&"|"&D4,'All Song Rankings'!$T:$T,0),0) -> 3 | G4: =IF(F4=0,"NOT FOUND",INDEX('All Song Rankings'!$A:$A,F4)) -> Shut Up and Dance | H4: =IF(F4=0,"NOT FOUND",INDEX('All Song Rankings'!$B:$B,F4)) -> WALK THE MOON | I4: =IF(F4=0,"NOT FOUND",INDEX('All Song Rankings'!$D:$D,F4)) -> Nicole | J4: =IF(F4=0,"NOT FOUND",IF(C4=I4,"SELF-VOTE",IF(COUNTIF($K:$K,K4)>1,"DUPLICATE","OK"))) -> OK | K4: =A4&"|"&B4&"|"&C4&"|"&D4 -> 1|1|Collin|spotify:track:4kbj5MwxO1bq9wjT5g9HaA
A5: 1 | B5: 1 | C5: Collin | D5: spotify:track:7usqgT1ajVAJ3s0wXePtRr | E5: 2 | F5: =IFERROR(MATCH(A5&"|"&B5&"|"&D5,'All Song Rankings'!$T:$T,0),0) -> 2 | G5: =IF(F5=0,"NOT FOUND",INDEX('All Song Rankings'!$A:$A,F5)) -> Love Me to Heaven | H5: =IF(F5=0,"NOT FOUND",INDEX('All Song Rankings'!$B:$B,F5)) -> Jonas Brothers | I5: =IF(F5=0,"NOT FOUND",INDEX('All Song Rankings'!$D:$D,F5)) -> Kelsey | J5: =IF(F5=0,"NOT FOUND",IF(C5=I5,"SELF-VOTE",IF(COUNTIF($K:$K,K5)>1,"DUPLICATE","OK"))) -> OK | K5: =A5&"|"&B5&"|"&C5&"|"&D5 -> 1|1|Collin|spotify:track:7usqgT1ajVAJ3s0wXePtRr
A6: 1 | B6: 1 | C6: Kelsey | D6: spotify:track:1GC1MIaRMW3kfVK9VyD5Ii | E6: 1 | F6: =IFERROR(MATCH(A6&"|"&B6&"|"&D6,'All Song Rankings'!$T:$T,0),0) -> 8 | G6: =IF(F6=0,"NOT FOUND",INDEX('All Song Rankings'!$A:$A,F6)) -> Tous les mêmes | H6: =IF(F6=0,"NOT FOUND",INDEX('All Song Rankings'!$B:$B,F6)) -> Stromae | I6: =IF(F6=0,"NOT FOUND",INDEX('All Song Rankings'!$D:$D,F6)) -> Matt | J6: =IF(F6=0,"NOT FOUND",IF(C6=I6,"SELF-VOTE",IF(COUNTIF($K:$K,K6)>1,"DUPLICATE","OK"))) -> OK | K6: =A6&"|"&B6&"|"&C6&"|"&D6 -> 1|1|Kelsey|spotify:track:1GC1MIaRMW3kfVK9VyD5Ii
A7: 1 | B7: 1 | C7: Kelsey | D7: spotify:track:1MAXdOA4Dtz6eJMz0nEq2H | E7: 1 | F7: =IFERROR(MATCH(A7&"|"&B7&"|"&D7,'All Song Rankings'!$T:$T,0),0) -> 5 | G7: =IF(F7=0,"NOT FOUND",INDEX('All Song Rankings'!$A:$A,F7)) -> Lonely Heart | H7: =IF(F7=0,"NOT FOUND",INDEX('All Song Rankings'!$B:$B,F7)) -> 5 Seconds of Summer | I7: =IF(F7=0,"NOT FOUND",INDEX('All Song Rankings'!$D:$D,F7)) -> Merita | J7: =IF(F7=0,"NOT FOUND",IF(C7=I7,"SELF-VOTE",IF(COUNTIF($K:$K,K7)>1,"DUPLICATE","OK"))) -> OK | K7: =A7&"|"&B7&"|"&C7&"|"&D7 -> 1|1|Kelsey|spotify:track:1MAXdOA4Dtz6eJMz0nEq2H
A8: 1 | B8: 1 | C8: Kelsey | D8: spotify:track:1XwAKjAZ1xDZOcuyZoqce4 | E8: 1 | F8: =IFERROR(MATCH(A8&"|"&B8&"|"&D8,'All Song Rankings'!$T:$T,0),0) -> 11 | G8: =IF(F8=0,"NOT FOUND",INDEX('All Song Rankings'!$A:$A,F8)) -> Moon River | H8: =IF(F8=0,"NOT FOUND",INDEX('All Song Rankings'!$B:$B,F8)) -> Audrey Hepburn | I8: =IF(F8=0,"NOT FOUND",INDEX('All Song Rankings'!$D:$D,F8)) -> Logan | J8: =IF(F8=0,"NOT FOUND",IF(C8=I8,"SELF-VOTE",IF(COUNTIF($K:$K,K8)>1,"DUPLICATE","OK"))) -> OK | K8: =A8&"|"&B8&"|"&C8&"|"&D8 -> 1|1|Kelsey|spotify:track:1XwAKjAZ1xDZOcuyZoqce4
A9: 1 | B9: 1 | C9: Kelsey | D9: spotify:track:3U5JVgI2x4rDyHGObzJfNf | E9: 1 | F9: =IFERROR(MATCH(A9&"|"&B9&"|"&D9,'All Song Rankings'!$T:$T,0),0) -> 10 | G9: =IF(F9=0,"NOT FOUND",INDEX('All Song Rankings'!$A:$A,F9)) -> Unwritten | H9: =IF(F9=0,"NOT FOUND",INDEX('All Song Rankings'!$B:$B,F9)) -> Natasha Bedingfield | I9: =IF(F9=0,"NOT FOUND",INDEX('All Song Rankings'!$D:$D,F9)) -> Olivia | J9: =IF(F9=0,"NOT FOUND",IF(C9=I9,"SELF-VOTE",IF(COUNTIF($K:$K,K9)>1,"DUPLICATE","OK"))) -> OK | K9: =A9&"|"&B9&"|"&C9&"|"&D9 -> 1|1|Kelsey|spotify:track:3U5JVgI2x4rDyHGObzJfNf
A10: 1 | B10: 1 | C10: Kelsey | D10: spotify:track:3hZIvVYZWsuFpdWdXQFgKx | E10: 1 | F10: =IFERROR(MATCH(A10&"|"&B10&"|"&D10,'All Song Rankings'!$T:$T,0),0) -> 6 | G10: =IF(F10=0,"NOT FOUND",INDEX('All Song Rankings'!$A:$A,F10)) -> Euclid | H10: =IF(F10=0,"NOT FOUND",INDEX('All Song Rankings'!$B:$B,F10)) -> Sleep Token | I10: =IF(F10=0,"NOT FOUND",INDEX('All Song Rankings'!$D:$D,F10)) -> Kristen | J10: =IF(F10=0,"NOT FOUND",IF(C10=I10,"SELF-VOTE",IF(COUNTIF($K:$K,K10)>1,"DUPLICATE","OK"))) -> OK | K10: =A10&"|"&B10&"|"&C10&"|"&D10 -> 1|1|Kelsey|spotify:track:3hZIvVYZWsuFpdWdXQFgKx
A11: 1 | B11: 1 | C11: Kelsey | D11: spotify:track:4kbj5MwxO1bq9wjT5g9HaA | E11: 2 | F11: =IFERROR(MATCH(A11&"|"&B11&"|"&D11,'All Song Rankings'!$T:$T,0),0) -> 3 | G11: =IF(F11=0,"NOT FOUND",INDEX('All Song Rankings'!$A:$A,F11)) -> Shut Up and Dance | H11: =IF(F11=0,"NOT FOUND",INDEX('All Song Rankings'!$B:$B,F11)) -> WALK THE MOON | I11: =IF(F11=0,"NOT FOUND",INDEX('All Song Rankings'!$D:$D,F11)) -> Nicole | J11: =IF(F11=0,"NOT FOUND",IF(C11=I11,"SELF-VOTE",IF(COUNTIF($K:$K,K11)>1,"DUPLICATE","OK"))) -> OK | K11: =A11&"|"&B11&"|"&C11&"|"&D11 -> 1|1|Kelsey|spotify:track:4kbj5MwxO1bq9wjT5g9HaA
A12: 1 | B12: 1 | C12: Kelsey | D12: spotify:track:5FtOZv6MB6IWL2DneVYvoe | E12: 1 | F12: =IFERROR(MATCH(A12&"|"&B12&"|"&D12,'All Song Rankings'!$T:$T,0),0) -> 7 | G12: =IF(F12=0,"NOT FOUND",INDEX('All Song Rankings'!$A:$A,F12)) -> By My Side | H12: =IF(F12=0,"NOT FOUND",INDEX('All Song Rankings'!$B:$B,F12)) -> Connor Price | I12: =IF(F12=0,"NOT FOUND",INDEX('All Song Rankings'!$D:$D,F12)) -> Collin | J12: =IF(F12=0,"NOT FOUND",IF(C12=I12,"SELF-VOTE",IF(COUNTIF($K:$K,K12)>1,"DUPLICATE","OK"))) -> OK | K12: =A12&"|"&B12&"|"&C12&"|"&D12 -> 1|1|Kelsey|spotify:track:5FtOZv6MB6IWL2DneVYvoe
A13: 1 | B13: 1 | C13: Kelsey | D13: spotify:track:5Qn0AlYJHOKogfbE36or9V | E13: 1 | F13: =IFERROR(MATCH(A13&"|"&B13&"|"&D13,'All Song Rankings'!$T:$T,0),0) -> 12 | G13: =IF(F13=0,"NOT FOUND",INDEX('All Song Rankings'!$A:$A,F13)) -> At the Beginning | H13: =IF(F13=0,"NOT FOUND",INDEX('All Song Rankings'!$B:$B,F13)) -> Hollywood Sound Stars | I13: =IF(F13=0,"NOT FOUND",INDEX('All Song Rankings'!$D:$D,F13)) -> Maryann | J13: =IF(F13=0,"NOT FOUND",IF(C13=I13,"SELF-VOTE",IF(COUNTIF($K:$K,K13)>1,"DUPLICATE","OK"))) -> OK | K13: =A13&"|"&B13&"|"&C13&"|"&D13 -> 1|1|Kelsey|spotify:track:5Qn0AlYJHOKogfbE36or9V
... A5289: 7 | B5289: 8 | C5289: Stephanie | D5289: spotify:track:7jwQlYGpOml9ETGre1HqGA | E5289: 1 | F5289: =IFERROR(MATCH(A5289&"|"&B5289&"|"&D5289,'All Song Rankings'!$T:$T,0),0) -> 775 | G5289: =IF(F5289=0,"NOT FOUND",INDEX('All Song Rankings'!$A:$A,F5289)) -> Somebody's Watching Me | H5289: =IF(F5289=0,"NOT FOUND",INDEX('All Song Rankings'!$B:$B,F5289)) -> Rockwell | I5289: =IF(F5289=0,"NOT FOUND",INDEX('All Song Rankings'!$D:$D,F5289)) -> Sara | J5289: =IF(F5289=0,"NOT FOUND",IF(C5289=I5289,"SELF-VOTE",IF(COUNTIF($K:$K,K5289)>1,"DUPLICATE","OK"))) -> OK | K5289: =A5289&"|"&B5289&"|"&C5289&"|"&D5289 -> 7|8|Stephanie|spotify:track:7jwQlYGpOml9ETGre1HqGA

Sheet Rounds
A1: League # | B1: League | C1: Round # | D1: Round Name | E1: Description | F1: Point Budget | G1: Songs per Person | H1: Submissions | I1: Forfeited Songs | J1: Voters | K1: Status | L1: Playlist URL | M1: Max Votes per Song
A2: 1 | B2: Org Mgmt COE (1st League) | C2: 1 | D2: A Song you'd recommend any day | F2: 10 | G2: 1 | H2: =COUNTIFS('All Song Rankings'!$J:$J,A2,'All Song Rankings'!$K:$K,C2) -> 11 | I2: =COUNTIFS('All Song Rankings'!$J:$J,A2,'All Song Rankings'!$K:$K,C2,'All Song Rankings'!$Q:$Q,"Forfeited") -> 0 | J2: =SUMPRODUCT(--(COUNTIFS(Votes!$A:$A,A2,Votes!$B:$B,C2,Votes!$C:$C,Participants!$A$2:$A$200)>0)) -> 11 | K2: =IF(H2=0,"Not started",IF(COUNTIFS('All Song Rankings'!$J:$J,A2,'All Song Rankings'!$K:$K,C2,'All Song Rankings'!$F:$F,">=0")=0,"Unscored","Scored")) -> Scored | L2: https://open.spotify.com/playlist/3kPMtXos73C2xQmMQvPGPx
A3: 1 | B3: Org Mgmt COE (1st League) | C3: 2 | D3: Halloween-ish Songs | F3: 10 | G3: 1 | H3: =COUNTIFS('All Song Rankings'!$J:$J,A3,'All Song Rankings'!$K:$K,C3) -> 11 | I3: =COUNTIFS('All Song Rankings'!$J:$J,A3,'All Song Rankings'!$K:$K,C3,'All Song Rankings'!$Q:$Q,"Forfeited") -> 0 | J3: =SUMPRODUCT(--(COUNTIFS(Votes!$A:$A,A3,Votes!$B:$B,C3,Votes!$C:$C,Participants!$A$2:$A$200)>0)) -> 11 | K3: =IF(H3=0,"Not started",IF(COUNTIFS('All Song Rankings'!$J:$J,A3,'All Song Rankings'!$K:$K,C3,'All Song Rankings'!$F:$F,">=0")=0,"Unscored","Scored")) -> Scored | L3: https://open.spotify.com/playlist/3JaCvioVBW6DIpEJz4Tagl
A4: 1 | B4: Org Mgmt COE (1st League) | C4: 3 | D4: Please Rise - You are now in charge of a country! What is the national anthem? | F4: 10 | G4: 1 | H4: =COUNTIFS('All Song Rankings'!$J:$J,A4,'All Song Rankings'!$K:$K,C4) -> 10 | I4: =COUNTIFS('All Song Rankings'!$J:$J,A4,'All Song Rankings'!$K:$K,C4,'All Song Rankings'!$Q:$Q,"Forfeited") -> 0 | J4: =SUMPRODUCT(--(COUNTIFS(Votes!$A:$A,A4,Votes!$B:$B,C4,Votes!$C:$C,Participants!$A$2:$A$200)>0)) -> 10 | K4: =IF(H4=0,"Not started",IF(COUNTIFS('All Song Rankings'!$J:$J,A4,'All Song Rankings'!$K:$K,C4,'All Song Rankings'!$F:$F,">=0")=0,"Unscored","Scored")) -> Scored | L4: https://open.spotify.com/playlist/42E7CG7xy9VKDUjJ42KfjN
A5: 1 | B5: Org Mgmt COE (1st League) | C5: 4 | D5: Deep Cut Song from a Popular Artist | F5: 10 | G5: 1 | H5: =COUNTIFS('All Song Rankings'!$J:$J,A5,'All Song Rankings'!$K:$K,C5) -> 9 | I5: =COUNTIFS('All Song Rankings'!$J:$J,A5,'All Song Rankings'!$K:$K,C5,'All Song Rankings'!$Q:$Q,"Forfeited") -> 0 | J5: =SUMPRODUCT(--(COUNTIFS(Votes!$A:$A,A5,Votes!$B:$B,C5,Votes!$C:$C,Participants!$A$2:$A$200)>0)) -> 9 | K5: =IF(H5=0,"Not started",IF(COUNTIFS('All Song Rankings'!$J:$J,A5,'All Song Rankings'!$K:$K,C5,'All Song Rankings'!$F:$F,">=0")=0,"Unscored","Scored")) -> Scored | L5: https://open.spotify.com/playlist/5rIguViPV6R2Bkr1Wc4Sb0
A6: 1 | B6: Org Mgmt COE (1st League) | C6: 5 | D6: Songs that "cut deep" (A Good Cry Song) | E6: 💙😭🤧🎶 | F6: 10 | G6: 1 | H6: =COUNTIFS('All Song Rankings'!$J:$J,A6,'All Song Rankings'!$K:$K,C6) -> 10 | I6: =COUNTIFS('All Song Rankings'!$J:$J,A6,'All Song Rankings'!$K:$K,C6,'All Song Rankings'!$Q:$Q,"Forfeited") -> 0 | J6: =SUMPRODUCT(--(COUNTIFS(Votes!$A:$A,A6,Votes!$B:$B,C6,Votes!$C:$C,Participants!$A$2:$A$200)>0)) -> 10 | K6: =IF(H6=0,"Not started",IF(COUNTIFS('All Song Rankings'!$J:$J,A6,'All Song Rankings'!$K:$K,C6,'All Song Rankings'!$F:$F,">=0")=0,"Unscored","Scored")) -> Scored | L6: https://open.spotify.com/playlist/6bRXBYvMGqY1O4idh3i9z9
A7: 1 | B7: Org Mgmt COE (1st League) | C7: 6 | D7: Songs that tell a Story | E7: Pick a track with a clear narrative. Lyrics must drive the story. | F7: 10 | G7: 1 | H7: =COUNTIFS('All Song Rankings'!$J:$J,A7,'All Song Rankings'!$K:$K,C7) -> 11 | I7: =COUNTIFS('All Song Rankings'!$J:$J,A7,'All Song Rankings'!$K:$K,C7,'All Song Rankings'!$Q:$Q,"Forfeited") -> 1 | J7: =SUMPRODUCT(--(COUNTIFS(Votes!$A:$A,A7,Votes!$B:$B,C7,Votes!$C:$C,Participants!$A$2:$A$200)>0)) -> 10 | K7: =IF(H7=0,"Not started",IF(COUNTIFS('All Song Rankings'!$J:$J,A7,'All Song Rankings'!$K:$K,C7,'All Song Rankings'!$F:$F,">=0")=0,"Unscored","Scored")) -> Scored | L7: https://open.spotify.com/playlist/2MfyMRzfTv6Jf0Stip2gJO
A8: 1 | B8: Org Mgmt COE (1st League) | C8: 7 | D8: Artist nobody knows but you? | E8: Pick an artist you genuinely think others in the league might not know or have never listened to. Vote for songs that truly surprised you, felt fresh, or made you want to dig into the artist’s catalog. | F8: 10 | G8: 1 | H8: =COUNTIFS('All Song Rankings'!$J:$J,A8,'All Song Rankings'!$K:$K,C8) -> 11 | I8: =COUNTIFS('All Song Rankings'!$J:$J,A8,'All Song Rankings'!$K:$K,C8,'All Song Rankings'!$Q:$Q,"Forfeited") -> 0 | J8: =SUMPRODUCT(--(COUNTIFS(Votes!$A:$A,A8,Votes!$B:$B,C8,Votes!$C:$C,Participants!$A$2:$A$200)>0)) -> 11 | K8: =IF(H8=0,"Not started",IF(COUNTIFS('All Song Rankings'!$J:$J,A8,'All Song Rankings'!$K:$K,C8,'All Song Rankings'!$F:$F,">=0")=0,"Unscored","Scored")) -> Scored | L8: https://open.spotify.com/playlist/3bt6V6J6tV0WhTC4rpNPRZ
A9: 1 | B9: Org Mgmt COE (1st League) | C9: 8 | D9: Best Earworm | E9: Pick a song that is irresistably catchy - something that sticks in your head after one listen. | F9: 10 | G9: 1 | H9: =COUNTIFS('All Song Rankings'!$J:$J,A9,'All Song Rankings'!$K:$K,C9) -> 12 | I9: =COUNTIFS('All Song Rankings'!$J:$J,A9,'All Song Rankings'!$K:$K,C9,'All Song Rankings'!$Q:$Q,"Forfeited") -> 0 | J9: =SUMPRODUCT(--(COUNTIFS(Votes!$A:$A,A9,Votes!$B:$B,C9,Votes!$C:$C,Participants!$A$2:$A$200)>0)) -> 12 | K9: =IF(H9=0,"Not started",IF(COUNTIFS('All Song Rankings'!$J:$J,A9,'All Song Rankings'!$K:$K,C9,'All Song Rankings'!$F:$F,">=0")=0,"Unscored","Scored")) -> Scored | L9: https://open.spotify.com/playlist/3gC9IZWwG01NmFHanuBQu6
A10: 2 | B10: Org Mgmt: The Sequel (2nd League) | C10: 1 | D10: Workout Song | E10: Songs that make you feel unstoppable. High energy, hype tracks, or anything you’d put on while sprinting, lifting, or surviving a treadmill incline from hell. | F10: 10 | G10: 1 | H10: =COUNTIFS('All Song Rankings'!$J:$J,A10,'All Song Rankings'!$K:$K,C10) -> 14 | I10: =COUNTIFS('All Song Rankings'!$J:$J,A10,'All Song Rankings'!$K:$K,C10,'All Song Rankings'!$Q:$Q,"Forfeited") -> 0 | J10: =SUMPRODUCT(--(COUNTIFS(Votes!$A:$A,A10,Votes!$B:$B,C10,Votes!$C:$C,Participants!$A$2:$A$200)>0)) -> 14 | K10: =IF(H10=0,"Not started",IF(COUNTIFS('All Song Rankings'!$J:$J,A10,'All Song Rankings'!$K:$K,C10,'All Song Rankings'!$F:$F,">=0")=0,"Unscored","Scored")) -> Scored | L10: https://open.spotify.com/playlist/2jsEQvgykIMJMMTioBu19b
A11: 2 | B11: Org Mgmt: The Sequel (2nd League) | C11: 2 | D11: Hidden Holiday Gems | E11: Celebrate the season with festive tracks that aren’t the usual overplayed hits. Underrated, lesser-known, or offbeat holiday songs only. | F11: 10 | G11: 1 | H11: =COUNTIFS('All Song Rankings'!$J:$J,A11,'All Song Rankings'!$K:$K,C11) -> 14 | I11: =COUNTIFS('All Song Rankings'!$J:$J,A11,'All Song Rankings'!$K:$K,C11,'All Song Rankings'!$Q:$Q,"Forfeited") -> 0 | J11: =SUMPRODUCT(--(COUNTIFS(Votes!$A:$A,A11,Votes!$B:$B,C11,Votes!$C:$C,Participants!$A$2:$A$200)>0)) -> 14 | K11: =IF(H11=0,"Not started",IF(COUNTIFS('All Song Rankings'!$J:$J,A11,'All Song Rankings'!$K:$K,C11,'All Song Rankings'!$F:$F,">=0")=0,"Unscored","Scored")) -> Scored | L11: https://open.spotify.com/playlist/3KZSy1W3Sfv0ib5pjH3yyx
A12: 2 | B12: Org Mgmt: The Sequel (2nd League) | C12: 3 | D12: Mystery (I'm Happy, Why Do You Ask?) | E12: Submit whatever you want—no explanation, no category. Everyone only finds out the theme after the songs are revealed. | F12: 10 | G12: 1 | H12: =COUNTIFS('All Song Rankings'!$J:$J,A12,'All Song Rankings'!$K:$K,C12) -> 15 | I12: =COUNTIFS('All Song Rankings'!$J:$J,A12,'All Song Rankings'!$K:$K,C12,'All Song Rankings'!$Q:$Q,"Forfeited") -> 0 | J12: =SUMPRODUCT(--(COUNTIFS(Votes!$A:$A,A12,Votes!$B:$B,C12,Votes!$C:$C,Participants!$A$2:$A$200)>0)) -> 15 | K12: =IF(H12=0,"Not started",IF(COUNTIFS('All Song Rankings'!$J:$J,A12,'All Song Rankings'!$K:$K,C12,'All Song Rankings'!$F:$F,">=0")=0,"Unscored","Scored")) -> Scored | L12: https://open.spotify.com/playlist/6ETKItmgRQ4XBn4kbDL5T9
A13: 2 | B13: Org Mgmt: The Sequel (2nd League) | C13: 4 | D13: Songs from Another World | E13: Tracks that feel alien, ethereal, futuristic, other-dimensional, or just… not from Earth. | F13: 10 | G13: 1 | H13: =COUNTIFS('All Song Rankings'!$J:$J,A13,'All Song Rankings'!$K:$K,C13) -> 14 | I13: =COUNTIFS('All Song Rankings'!$J:$J,A13,'All Song Rankings'!$K:$K,C13,'All Song Rankings'!$Q:$Q,"Forfeited") -> 3 | J13: =SUMPRODUCT(--(COUNTIFS(Votes!$A:$A,A13,Votes!$B:$B,C13,Votes!$C:$C,Participants!$A$2:$A$200)>0)) -> 11 | K13: =IF(H13=0,"Not started",IF(COUNTIFS('All Song Rankings'!$J:$J,A13,'All Song Rankings'!$K:$K,C13,'All Song Rankings'!$F:$F,">=0")=0,"Unscored","Scored")) -> Scored | L13: https://open.spotify.com/playlist/6LfdnlE8afPryUOLEqDdeR
A14: 2 | B14: Org Mgmt: The Sequel (2nd League) | C14: 5 | D14: The cover was better than the original | E14: Submit a cover version that you genuinely believe surpasses the original. Include the original artist in your submission comments. | F14: 10 | G14: 1 | H14: =COUNTIFS('All Song Rankings'!$J:$J,A14,'All Song Rankings'!$K:$K,C14) -> 12 | I14: =COUNTIFS('All Song Rankings'!$J:$J,A14,'All Song Rankings'!$K:$K,C14,'All Song Rankings'!$Q:$Q,"Forfeited") -> 2 | J14: =SUMPRODUCT(--(COUNTIFS(Votes!$A:$A,A14,Votes!$B:$B,C14,Votes!$C:$C,Participants!$A$2:$A$200)>0)) -> 10 | K14: =IF(H14=0,"Not started",IF(COUNTIFS('All Song Rankings'!$J:$J,A14,'All Song Rankings'!$K:$K,C14,'All Song Rankings'!$F:$F,">=0")=0,"Unscored","Scored")) -> Scored | L14: https://open.spotify.com/playlist/0fzGyTVOAGM9KVCTg4uJsh
A15: 2 | B15: Org Mgmt: The Sequel (2nd League) | C15: 6 | D15: Forgotten Gems | E15: Bring back a song that was once popular but has faded from mainstream memory. It has to be atleast 10 years old. | F15: 10 | G15: 1 | H15: =COUNTIFS('All Song Rankings'!$J:$J,A15,'All Song Rankings'!$K:$K,C15) -> 11 | I15: =COUNTIFS('All Song Rankings'!$J:$J,A15,'All Song Rankings'!$K:$K,C15,'All Song Rankings'!$Q:$Q,"Forfeited") -> 1 | J15: =SUMPRODUCT(--(COUNTIFS(Votes!$A:$A,A15,Votes!$B:$B,C15,Votes!$C:$C,Participants!$A$2:$A$200)>0)) -> 10 | K15: =IF(H15=0,"Not started",IF(COUNTIFS('All Song Rankings'!$J:$J,A15,'All Song Rankings'!$K:$K,C15,'All Song Rankings'!$F:$F,">=0")=0,"Unscored","Scored")) -> Scored | L15: https://open.spotify.com/playlist/5LMkIkt4COJNCmCbtiLzRc
A16: 2 | B16: Org Mgmt: The Sequel (2nd League) | C16: 7 | D16: Unexpected Collabs | E16: Choose a song featuring artists from different genres or surprising pairings. It should feel like an unlikely combo. | F16: 10 | G16: 1 | H16: =COUNTIFS('All Song Rankings'!$J:$J,A16,'All Song Rankings'!$K:$K,C16) -> 13 | I16: =COUNTIFS('All Song Rankings'!$J:$J,A16,'All Song Rankings'!$K:$K,C16,'All Song Rankings'!$Q:$Q,"Forfeited") -> 3 | J16: =SUMPRODUCT(--(COUNTIFS(Votes!$A:$A,A16,Votes!$B:$B,C16,Votes!$C:$C,Participants!$A$2:$A$200)>0)) -> 9 | K16: =IF(H16=0,"Not started",IF(COUNTIFS('All Song Rankings'!$J:$J,A16,'All Song Rankings'!$K:$K,C16,'All Song Rankings'!$F:$F,">=0")=0,"Unscored","Scored")) -> Scored | L16: https://open.spotify.com/playlist/1qs2e5iWuF5wDWBoFkDPCg
A17: 2 | B17: Org Mgmt: The Sequel (2nd League) | C17: 8 | D17: Villain Theme Song | E17: If you turned evil tomorrow, what song would play when you enter the room? Don't use songs that is already themed for a villain! | F17: 10 | G17: 1 | H17: =COUNTIFS('All Song Rankings'!$J:$J,A17,'All Song Rankings'!$K:$K,C17) -> 13 | I17: =COUNTIFS('All Song Rankings'!$J:$J,A17,'All Song Rankings'!$K:$K,C17,'All Song Rankings'!$Q:$Q,"Forfeited") -> 0 | J17: =SUMPRODUCT(--(COUNTIFS(Votes!$A:$A,A17,Votes!$B:$B,C17,Votes!$C:$C,Participants!$A$2:$A$200)>0)) -> 13 | K17: =IF(H17=0,"Not started",IF(COUNTIFS('All Song Rankings'!$J:$J,A17,'All Song Rankings'!$K:$K,C17,'All Song Rankings'!$F:$F,">=0")=0,"Unscored","Scored")) -> Scored | L17: https://open.spotify.com/playlist/1e1D6sYkiSYEY5KOGVKXds
... A57: 7 | B57: Lucky Number 7 (7th League) | C57: 8 | D57: After Hours | E57: Celebrate the witching hour for Halloween. Song that is spooky, eerie, supernatural, or delightfully creepy. | F57: 10 | G57: 1 | H57: =COUNTIFS('All Song Rankings'!$J:$J,A57,'All Song Rankings'!$K:$K,C57) -> 14 | I57: =COUNTIFS('All Song Rankings'!$J:$J,A57,'All Song Rankings'!$K:$K,C57,'All Song Rankings'!$Q:$Q,"Forfeited") -> 0 | J57: =SUMPRODUCT(--(COUNTIFS(Votes!$A:$A,A57,Votes!$B:$B,C57,Votes!$C:$C,Participants!$A$2:$A$200)>0)) -> 14 | K57: =IF(H57=0,"Not started",IF(COUNTIFS('All Song Rankings'!$J:$J,A57,'All Song Rankings'!$K:$K,C57,'All Song Rankings'!$F:$F,">=0")=0,"Unscored","Scored")) -> Scored | L57: https://open.spotify.com/playlist/196ySUUS9kdjN2ir3fgiQw
A58: 8 | B58: The Soundtrack of Us (8th League) | C58: 1 | D58: First Impressions | H58: =COUNTIFS('All Song Rankings'!$J:$J,A58,'All Song Rankings'!$K:$K,C58) -> 14 | I58: =COUNTIFS('All Song Rankings'!$J:$J,A58,'All Song Rankings'!$K:$K,C58,'All Song Rankings'!$Q:$Q,"Forfeited") -> 0 | J58: =SUMPRODUCT(--(COUNTIFS(Votes!$A:$A,A58,Votes!$B:$B,C58,Votes!$C:$C,Participants!$A$2:$A$200)>0)) -> 0 | K58: =IF(H58=0,"Not started",IF(COUNTIFS('All Song Rankings'!$J:$J,A58,'All Song Rankings'!$K:$K,C58,'All Song Rankings'!$F:$F,">=0")=0,"Unscored","Scored")) -> Unscored
A59: 8 | B59: The Soundtrack of Us (8th League) | C59: 2 | D59: Wait…That's Not the Lyric? | H59: =COUNTIFS('All Song Rankings'!$J:$J,A59,'All Song Rankings'!$K:$K,C59) -> 16 | I59: =COUNTIFS('All Song Rankings'!$J:$J,A59,'All Song Rankings'!$K:$K,C59,'All Song Rankings'!$Q:$Q,"Forfeited") -> 0 | J59: =SUMPRODUCT(--(COUNTIFS(Votes!$A:$A,A59,Votes!$B:$B,C59,Votes!$C:$C,Participants!$A$2:$A$200)>0)) -> 0 | K59: =IF(H59=0,"Not started",IF(COUNTIFS('All Song Rankings'!$J:$J,A59,'All Song Rankings'!$K:$K,C59,'All Song Rankings'!$F:$F,">=0")=0,"Unscored","Scored")) -> Unscored

Sheet Participants
A1: Name | B1: Export Username | C1: Leagues Submitted In | D1: Submissions | E1: Votes Cast | F1: Official Points Received | G1: Raw Points Received
A2: Anya | B2: Anya Pall | C2: =SUMPRODUCT(--(COUNTIFS('All Song Rankings'!$D:$D,A2,'All Song Rankings'!$J:$J,ROW($1:$20))>0)) -> 2 | D2: =COUNTIF('All Song Rankings'!$D:$D,A2) -> 6 | E2: =COUNTIF(Votes!$C:$C,A2) -> 22 | F2: =SUMIFS('All Song Rankings'!$F:$F,'All Song Rankings'!$D:$D,A2) -> 20 | G2: =SUMIFS('All Song Rankings'!$O:$O,'All Song Rankings'!$D:$D,A2) -> 43
A3: Aubrey | B3: Aubrey Colón | C3: =SUMPRODUCT(--(COUNTIFS('All Song Rankings'!$D:$D,A3,'All Song Rankings'!$J:$J,ROW($1:$20))>0)) -> 5 | D3: =COUNTIF('All Song Rankings'!$D:$D,A3) -> 29 | E3: =COUNTIF(Votes!$C:$C,A3) -> 160 | F3: =SUMIFS('All Song Rankings'!$F:$F,'All Song Rankings'!$D:$D,A3) -> 206 | G3: =SUMIFS('All Song Rankings'!$O:$O,'All Song Rankings'!$D:$D,A3) -> 263
A4: Christine | B4: Christine16 | C4: =SUMPRODUCT(--(COUNTIFS('All Song Rankings'!$D:$D,A4,'All Song Rankings'!$J:$J,ROW($1:$20))>0)) -> 5 | D4: =COUNTIF('All Song Rankings'!$D:$D,A4) -> 41 | E4: =COUNTIF(Votes!$C:$C,A4) -> 330 | F4: =SUMIFS('All Song Rankings'!$F:$F,'All Song Rankings'!$D:$D,A4) -> 322 | G4: =SUMIFS('All Song Rankings'!$O:$O,'All Song Rankings'!$D:$D,A4) -> 322
A5: Colleen | B5: Colleen | C5: =SUMPRODUCT(--(COUNTIFS('All Song Rankings'!$D:$D,A5,'All Song Rankings'!$J:$J,ROW($1:$20))>0)) -> 6 | D5: =COUNTIF('All Song Rankings'!$D:$D,A5) -> 41 | E5: =COUNTIF(Votes!$C:$C,A5) -> 297 | F5: =SUMIFS('All Song Rankings'!$F:$F,'All Song Rankings'!$D:$D,A5) -> 367 | G5: =SUMIFS('All Song Rankings'!$O:$O,'All Song Rankings'!$D:$D,A5) -> 410
A6: Collin | B6: dratrim | C6: =SUMPRODUCT(--(COUNTIFS('All Song Rankings'!$D:$D,A6,'All Song Rankings'!$J:$J,ROW($1:$20))>0)) -> 1 | D6: =COUNTIF('All Song Rankings'!$D:$D,A6) -> 8 | E6: =COUNTIF(Votes!$C:$C,A6) -> 35 | F6: =SUMIFS('All Song Rankings'!$F:$F,'All Song Rankings'!$D:$D,A6) -> 64 | G6: =SUMIFS('All Song Rankings'!$O:$O,'All Song Rankings'!$D:$D,A6) -> 64
A7: Grace | B7: Grace | C7: =SUMPRODUCT(--(COUNTIFS('All Song Rankings'!$D:$D,A7,'All Song Rankings'!$J:$J,ROW($1:$20))>0)) -> 6 | D7: =COUNTIF('All Song Rankings'!$D:$D,A7) -> 49 | E7: =COUNTIF(Votes!$C:$C,A7) -> 254 | F7: =SUMIFS('All Song Rankings'!$F:$F,'All Song Rankings'!$D:$D,A7) -> 400 | G7: =SUMIFS('All Song Rankings'!$O:$O,'All Song Rankings'!$D:$D,A7) -> 437
A8: Josh | B8: josh | C8: =SUMPRODUCT(--(COUNTIFS('All Song Rankings'!$D:$D,A8,'All Song Rankings'!$J:$J,ROW($1:$20))>0)) -> 2 | D8: =COUNTIF('All Song Rankings'!$D:$D,A8) -> 12 | E8: =COUNTIF(Votes!$C:$C,A8) -> 96 | F8: =SUMIFS('All Song Rankings'!$F:$F,'All Song Rankings'!$D:$D,A8) -> 112 | G8: =SUMIFS('All Song Rankings'!$O:$O,'All Song Rankings'!$D:$D,A8) -> 112
A9: Kelsey | B9: Kelsey Speicher | C9: =SUMPRODUCT(--(COUNTIFS('All Song Rankings'!$D:$D,A9,'All Song Rankings'!$J:$J,ROW($1:$20))>0)) -> 7 | D9: =COUNTIF('All Song Rankings'!$D:$D,A9) -> 56 | E9: =COUNTIF(Votes!$C:$C,A9) -> 395 | F9: =SUMIFS('All Song Rankings'!$F:$F,'All Song Rankings'!$D:$D,A9) -> 655 | G9: =SUMIFS('All Song Rankings'!$O:$O,'All Song Rankings'!$D:$D,A9) -> 655
A10: Kristen | B10: benkristenr | C10: =SUMPRODUCT(--(COUNTIFS('All Song Rankings'!$D:$D,A10,'All Song Rankings'!$J:$J,ROW($1:$20))>0)) -> 7 | D10: =COUNTIF('All Song Rankings'!$D:$D,A10) -> 57 | E10: =COUNTIF(Votes!$C:$C,A10) -> 414 | F10: =SUMIFS('All Song Rankings'!$F:$F,'All Song Rankings'!$D:$D,A10) -> 466 | G10: =SUMIFS('All Song Rankings'!$O:$O,'All Song Rankings'!$D:$D,A10) -> 477
A11: Leah | B11: Leah | C11: =SUMPRODUCT(--(COUNTIFS('All Song Rankings'!$D:$D,A11,'All Song Rankings'!$J:$J,ROW($1:$20))>0)) -> 7 | D11: =COUNTIF('All Song Rankings'!$D:$D,A11) -> 57 | E11: =COUNTIF(Votes!$C:$C,A11) -> 442 | F11: =SUMIFS('All Song Rankings'!$F:$F,'All Song Rankings'!$D:$D,A11) -> 591 | G11: =SUMIFS('All Song Rankings'!$O:$O,'All Song Rankings'!$D:$D,A11) -> 597
A12: Lisa | B12: Lisa | C12: =SUMPRODUCT(--(COUNTIFS('All Song Rankings'!$D:$D,A12,'All Song Rankings'!$J:$J,ROW($1:$20))>0)) -> 5 | D12: =COUNTIF('All Song Rankings'!$D:$D,A12) -> 41 | E12: =COUNTIF(Votes!$C:$C,A12) -> 293 | F12: =SUMIFS('All Song Rankings'!$F:$F,'All Song Rankings'!$D:$D,A12) -> 381 | G12: =SUMIFS('All Song Rankings'!$O:$O,'All Song Rankings'!$D:$D,A12) -> 381
A13: Logan | B13: Logan | C13: =SUMPRODUCT(--(COUNTIFS('All Song Rankings'!$D:$D,A13,'All Song Rankings'!$J:$J,ROW($1:$20))>0)) -> 7 | D13: =COUNTIF('All Song Rankings'!$D:$D,A13) -> 57 | E13: =COUNTIF(Votes!$C:$C,A13) -> 387 | F13: =SUMIFS('All Song Rankings'!$F:$F,'All Song Rankings'!$D:$D,A13) -> 568 | G13: =SUMIFS('All Song Rankings'!$O:$O,'All Song Rankings'!$D:$D,A13) -> 568
... A25: Stephanie | B25: Stephanie Lynn | C25: =SUMPRODUCT(--(COUNTIFS('All Song Rankings'!$D:$D,A25,'All Song Rankings'!$J:$J,ROW($1:$20))>0)) -> 7 | D25: =COUNTIF('All Song Rankings'!$D:$D,A25) -> 57 | E25: =COUNTIF(Votes!$C:$C,A25) -> 335 | F25: =SUMIFS('All Song Rankings'!$F:$F,'All Song Rankings'!$D:$D,A25) -> 543 | G25: =SUMIFS('All Song Rankings'!$O:$O,'All Song Rankings'!$D:$D,A25) -> 543

Sheet Music League Analytics
A1: Music League Analytics
A2: Formula-driven; updates automatically (replaces the old pivot tables, which had gone stale).
A4: Total submissions | B4: =COUNTA('All Song Rankings'!$A:$A)-1 -> 816
A5: Scored submissions | B5: =COUNTIF('All Song Rankings'!$F:$F,">=0") -> 786
A6: Unique tracks (by Spotify URI) | B6: =SUMPRODUCT(('All Song Rankings'!$L$2:$L$2000<>"")/COUNTIF('All Song Rankings'!$L$2:$L$2000,'All Song Rankings'!$L$2:$L$2000&"")) -> 764
A7: Unique artists | B7: =SUMPRODUCT(('All Song Rankings'!$B$2:$B$2000<>"")/COUNTIF('All Song Rankings'!$B$2:$B$2000,'All Song Rankings'!$B$2:$B$2000&"")) -> 634
A8: Participants | B8: =COUNTA(Participants!$A:$A)-1 -> 24
A9: Leagues | B9: =MAX(Rounds!$A:$A) -> 8
A10: By league
A11: League # | B11: League | C11: Rounds | D11: Songs | E11: Scored Songs | F11: Forfeited Songs | G11: Total Official Points | H11: Avg Points per Scored Song | I11: Submitters
A12: 1 | B12: =IFERROR(INDEX(Rounds!$B:$B,MATCH(A12,Rounds!$A:$A,0)),"") -> Org Mgmt COE (1st League) | C12: =COUNTIF(Rounds!$A:$A,A12) -> 8 | D12: =COUNTIF('All Song Rankings'!$J:$J,A12) -> 85 | E12: =COUNTIFS('All Song Rankings'!$J:$J,A12,'All Song Rankings'!$F:$F,">=0") -> 85 | F12: =COUNTIFS('All Song Rankings'!$J:$J,A12,'All Song Rankings'!$Q:$Q,"Forfeited") -> 1 | G12: =SUMIFS('All Song Rankings'!$F:$F,'All Song Rankings'!$J:$J,A12) -> 832 | H12: =IF(E12=0,"",G12/E12) -> 9.7882353 | I12: =SUMPRODUCT(--(COUNTIFS('All Song Rankings'!$D:$D,Participants!$A$2:$A$200,'All Song Rankings'!$J:$J,A12)>0)) -> 12
A13: 2 | B13: =IFERROR(INDEX(Rounds!$B:$B,MATCH(A13,Rounds!$A:$A,0)),"") -> Org Mgmt: The Sequel (2nd League) | C13: =COUNTIF(Rounds!$A:$A,A13) -> 8 | D13: =COUNTIF('All Song Rankings'!$J:$J,A13) -> 106 | E13: =COUNTIFS('All Song Rankings'!$J:$J,A13,'All Song Rankings'!$F:$F,">=0") -> 106 | F13: =COUNTIFS('All Song Rankings'!$J:$J,A13,'All Song Rankings'!$Q:$Q,"Forfeited") -> 9 | G13: =SUMIFS('All Song Rankings'!$F:$F,'All Song Rankings'!$J:$J,A13) -> 882 | H13: =IF(E13=0,"",G13/E13) -> 8.3207547 | I13: =SUMPRODUCT(--(COUNTIFS('All Song Rankings'!$D:$D,Participants!$A$2:$A$200,'All Song Rankings'!$J:$J,A13)>0)) -> 16
A14: 3 | B14: =IFERROR(INDEX(Rounds!$B:$B,MATCH(A14,Rounds!$A:$A,0)),"") -> Music League: tHReequel (3rd League) | C14: =COUNTIF(Rounds!$A:$A,A14) -> 8 | D14: =COUNTIF('All Song Rankings'!$J:$J,A14) -> 117 | E14: =COUNTIFS('All Song Rankings'!$J:$J,A14,'All Song Rankings'!$F:$F,">=0") -> 117 | F14: =COUNTIFS('All Song Rankings'!$J:$J,A14,'All Song Rankings'!$Q:$Q,"Forfeited") -> 5 | G14: =SUMIFS('All Song Rankings'!$F:$F,'All Song Rankings'!$J:$J,A14) -> 1080 | H14: =IF(E14=0,"",G14/E14) -> 9.2307692 | I14: =SUMPRODUCT(--(COUNTIFS('All Song Rankings'!$D:$D,Participants!$A$2:$A$200,'All Song Rankings'!$J:$J,A14)>0)) -> 15
A15: 4 | B15: =IFERROR(INDEX(Rounds!$B:$B,MATCH(A15,Rounds!$A:$A,0)),"") -> Episode IV: A New Playlist (4th League) | C15: =COUNTIF(Rounds!$A:$A,A15) -> 8 | D15: =COUNTIF('All Song Rankings'!$J:$J,A15) -> 110 | E15: =COUNTIFS('All Song Rankings'!$J:$J,A15,'All Song Rankings'!$F:$F,">=0") -> 110 | F15: =COUNTIFS('All Song Rankings'!$J:$J,A15,'All Song Rankings'!$Q:$Q,"Forfeited") -> 5 | G15: =SUMIFS('All Song Rankings'!$F:$F,'All Song Rankings'!$J:$J,A15) -> 942 | H15: =IF(E15=0,"",G15/E15) -> 8.5636364 | I15: =SUMPRODUCT(--(COUNTIFS('All Song Rankings'!$D:$D,Participants!$A$2:$A$200,'All Song Rankings'!$J:$J,A15)>0)) -> 14
A16: 5 | B16: =IFERROR(INDEX(Rounds!$B:$B,MATCH(A16,Rounds!$A:$A,0)),"") -> Episode V: The Playlist Strikes Back (5th League) | C16: =COUNTIF(Rounds!$A:$A,A16) -> 8 | D16: =COUNTIF('All Song Rankings'!$J:$J,A16) -> 131 | E16: =COUNTIFS('All Song Rankings'!$J:$J,A16,'All Song Rankings'!$F:$F,">=0") -> 131 | F16: =COUNTIFS('All Song Rankings'!$J:$J,A16,'All Song Rankings'!$Q:$Q,"Forfeited") -> 4 | G16: =SUMIFS('All Song Rankings'!$F:$F,'All Song Rankings'!$J:$J,A16) -> 1237 | H16: =IF(E16=0,"",G16/E16) -> 9.4427481 | I16: =SUMPRODUCT(--(COUNTIFS('All Song Rankings'!$D:$D,Participants!$A$2:$A$200,'All Song Rankings'!$J:$J,A16)>0)) -> 16
A17: 6 | B17: =IFERROR(INDEX(Rounds!$B:$B,MATCH(A17,Rounds!$A:$A,0)),"") -> Episode VI: Return of the Playlist (6th League) | C17: =COUNTIF(Rounds!$A:$A,A17) -> 8 | D17: =COUNTIF('All Song Rankings'!$J:$J,A17) -> 120 | E17: =COUNTIFS('All Song Rankings'!$J:$J,A17,'All Song Rankings'!$F:$F,">=0") -> 120 | F17: =COUNTIFS('All Song Rankings'!$J:$J,A17,'All Song Rankings'!$Q:$Q,"Forfeited") -> 7 | G17: =SUMIFS('All Song Rankings'!$F:$F,'All Song Rankings'!$J:$J,A17) -> 1059 | H17: =IF(E17=0,"",G17/E17) -> 8.825 | I17: =SUMPRODUCT(--(COUNTIFS('All Song Rankings'!$D:$D,Participants!$A$2:$A$200,'All Song Rankings'!$J:$J,A17)>0)) -> 16
A18: 7 | B18: =IFERROR(INDEX(Rounds!$B:$B,MATCH(A18,Rounds!$A:$A,0)),"") -> Lucky Number 7 (7th League) | C18: =COUNTIF(Rounds!$A:$A,A18) -> 8 | D18: =COUNTIF('All Song Rankings'!$J:$J,A18) -> 117 | E18: =COUNTIFS('All Song Rankings'!$J:$J,A18,'All Song Rankings'!$F:$F,">=0") -> 117 | F18: =COUNTIFS('All Song Rankings'!$J:$J,A18,'All Song Rankings'!$Q:$Q,"Forfeited") -> 9 | G18: =SUMIFS('All Song Rankings'!$F:$F,'All Song Rankings'!$J:$J,A18) -> 1011 | H18: =IF(E18=0,"",G18/E18) -> 8.6410256 | I18: =SUMPRODUCT(--(COUNTIFS('All Song Rankings'!$D:$D,Participants!$A$2:$A$200,'All Song Rankings'!$J:$J,A18)>0)) -> 16
A19: 8 | B19: =IFERROR(INDEX(Rounds!$B:$B,MATCH(A19,Rounds!$A:$A,0)),"") -> The Soundtrack of Us (8th League) | C19: =COUNTIF(Rounds!$A:$A,A19) -> 2 | D19: =COUNTIF('All Song Rankings'!$J:$J,A19) -> 30 | E19: =COUNTIFS('All Song Rankings'!$J:$J,A19,'All Song Rankings'!$F:$F,">=0") -> 0 | F19: =COUNTIFS('All Song Rankings'!$J:$J,A19,'All Song Rankings'!$Q:$Q,"Forfeited") -> 0 | G19: =SUMIFS('All Song Rankings'!$F:$F,'All Song Rankings'!$J:$J,A19) -> 0 | H19: =IF(E19=0,"",G19/E19) | I19: =SUMPRODUCT(--(COUNTIFS('All Song Rankings'!$D:$D,Participants!$A$2:$A$200,'All Song Rankings'!$J:$J,A19)>0)) -> 0
A21: By genre (Genre column)
A22: Genre | B22: Songs | C22: Share of Songs | D22: Total Official Points | E22: Avg Points per Scored Song
A23: =Lists!A2 -> A Cappella | B23: =COUNTIF('All Song Rankings'!$C:$C,A23) -> 2 | C23: =B23/$B$4 -> 0.0024509804 | D23: =SUMIFS('All Song Rankings'!$F:$F,'All Song Rankings'!$C:$C,A23) -> 25 | E23: =IF(COUNTIFS('All Song Rankings'!$C:$C,A23,'All Song Rankings'!$F:$F,">=0")=0,"",D23/COUNTIFS('All Song Rankings'!$C:$C,A23,'All Song Rankings'!$F:$F,">=0")) -> 12.5
A24: =Lists!A3 -> Alternative/Comedy | B24: =COUNTIF('All Song Rankings'!$C:$C,A24) -> 2 | C24: =B24/$B$4 -> 0.0024509804 | D24: =SUMIFS('All Song Rankings'!$F:$F,'All Song Rankings'!$C:$C,A24) -> 20 | E24: =IF(COUNTIFS('All Song Rankings'!$C:$C,A24,'All Song Rankings'!$F:$F,">=0")=0,"",D24/COUNTIFS('All Song Rankings'!$C:$C,A24,'All Song Rankings'!$F:$F,">=0")) -> 10
A25: =Lists!A4 -> Christian/Gospel | B25: =COUNTIF('All Song Rankings'!$C:$C,A25) -> 4 | C25: =B25/$B$4 -> 0.0049019608 | D25: =SUMIFS('All Song Rankings'!$F:$F,'All Song Rankings'!$C:$C,A25) -> 25 | E25: =IF(COUNTIFS('All Song Rankings'!$C:$C,A25,'All Song Rankings'!$F:$F,">=0")=0,"",D25/COUNTIFS('All Song Rankings'!$C:$C,A25,'All Song Rankings'!$F:$F,">=0")) -> 6.25
A26: =Lists!A5 -> Classical Crossover | B26: =COUNTIF('All Song Rankings'!$C:$C,A26) -> 3 | C26: =B26/$B$4 -> 0.0036764706 | D26: =SUMIFS('All Song Rankings'!$F:$F,'All Song Rankings'!$C:$C,A26) -> 37 | E26: =IF(COUNTIFS('All Song Rankings'!$C:$C,A26,'All Song Rankings'!$F:$F,">=0")=0,"",D26/COUNTIFS('All Song Rankings'!$C:$C,A26,'All Song Rankings'!$F:$F,">=0")) -> 12.333333
A27: =Lists!A6 -> Classical/Score | B27: =COUNTIF('All Song Rankings'!$C:$C,A27) -> 17 | C27: =B27/$B$4 -> 0.020833333 | D27: =SUMIFS('All Song Rankings'!$F:$F,'All Song Rankings'!$C:$C,A27) -> 133 | E27: =IF(COUNTIFS('All Song Rankings'!$C:$C,A27,'All Song Rankings'!$F:$F,">=0")=0,"",D27/COUNTIFS('All Song Rankings'!$C:$C,A27,'All Song Rankings'!$F:$F,">=0")) -> 7.8235294
A28: =Lists!A7 -> Country | B28: =COUNTIF('All Song Rankings'!$C:$C,A28) -> 46 | C28: =B28/$B$4 -> 0.056372549 | D28: =SUMIFS('All Song Rankings'!$F:$F,'All Song Rankings'!$C:$C,A28) -> 367 | E28: =IF(COUNTIFS('All Song Rankings'!$C:$C,A28,'All Song Rankings'!$F:$F,">=0")=0,"",D28/COUNTIFS('All Song Rankings'!$C:$C,A28,'All Song Rankings'!$F:$F,">=0")) -> 8.1555556
A29: =Lists!A8 -> Disco | B29: =COUNTIF('All Song Rankings'!$C:$C,A29) -> 2 | C29: =B29/$B$4 -> 0.0024509804 | D29: =SUMIFS('All Song Rankings'!$F:$F,'All Song Rankings'!$C:$C,A29) -> 9 | E29: =IF(COUNTIFS('All Song Rankings'!$C:$C,A29,'All Song Rankings'!$F:$F,">=0")=0,"",D29/COUNTIFS('All Song Rankings'!$C:$C,A29,'All Song Rankings'!$F:$F,">=0")) -> 9
A30: =Lists!A9 -> Electronic/Dance | B30: =COUNTIF('All Song Rankings'!$C:$C,A30) -> 32 | C30: =B30/$B$4 -> 0.039215686 | D30: =SUMIFS('All Song Rankings'!$F:$F,'All Song Rankings'!$C:$C,A30) -> 279 | E30: =IF(COUNTIFS('All Song Rankings'!$C:$C,A30,'All Song Rankings'!$F:$F,">=0")=0,"",D30/COUNTIFS('All Song Rankings'!$C:$C,A30,'All Song Rankings'!$F:$F,">=0")) -> 8.71875
A31: =Lists!A10 -> Folk/Americana | B31: =COUNTIF('All Song Rankings'!$C:$C,A31) -> 30 | C31: =B31/$B$4 -> 0.036764706 | D31: =SUMIFS('All Song Rankings'!$F:$F,'All Song Rankings'!$C:$C,A31) -> 245 | E31: =IF(COUNTIFS('All Song Rankings'!$C:$C,A31,'All Song Rankings'!$F:$F,">=0")=0,"",D31/COUNTIFS('All Song Rankings'!$C:$C,A31,'All Song Rankings'!$F:$F,">=0")) -> 8.1666667
A32: =Lists!A11 -> Hip-Hop/Rap | B32: =COUNTIF('All Song Rankings'!$C:$C,A32) -> 44 | C32: =B32/$B$4 -> 0.053921569 | D32: =SUMIFS('All Song Rankings'!$F:$F,'All Song Rankings'!$C:$C,A32) -> 371 | E32: =IF(COUNTIFS('All Song Rankings'!$C:$C,A32,'All Song Rankings'!$F:$F,">=0")=0,"",D32/COUNTIFS('All Song Rankings'!$C:$C,A32,'All Song Rankings'!$F:$F,">=0")) -> 8.8333333
A33: =Lists!A12 -> Indian Film Music | B33: =COUNTIF('All Song Rankings'!$C:$C,A33) -> 2 | C33: =B33/$B$4 -> 0.0024509804 | D33: =SUMIFS('All Song Rankings'!$F:$F,'All Song Rankings'!$C:$C,A33) -> 17 | E33: =IF(COUNTIFS('All Song Rankings'!$C:$C,A33,'All Song Rankings'!$F:$F,">=0")=0,"",D33/COUNTIFS('All Song Rankings'!$C:$C,A33,'All Song Rankings'!$F:$F,">=0")) -> 8.5
A34: =Lists!A13 -> Jazz/Vocal | B34: =COUNTIF('All Song Rankings'!$C:$C,A34) -> 15 | C34: =B34/$B$4 -> 0.018382353 | D34: =SUMIFS('All Song Rankings'!$F:$F,'All Song Rankings'!$C:$C,A34) -> 136 | E34: =IF(COUNTIFS('All Song Rankings'!$C:$C,A34,'All Song Rankings'!$F:$F,">=0")=0,"",D34/COUNTIFS('All Song Rankings'!$C:$C,A34,'All Song Rankings'!$F:$F,">=0")) -> 9.0666667
... A44: =Lists!A23 -> Soundtrack/Musical | B44: =COUNTIF('All Song Rankings'!$C:$C,A44) -> 49 | C44: =B44/$B$4 -> 0.06004902 | D44: =SUMIFS('All Song Rankings'!$F:$F,'All Song Rankings'!$C:$C,A44) -> 478 | E44: =IF(COUNTIFS('All Song Rankings'!$C:$C,A44,'All Song Rankings'!$F:$F,">=0")=0,"",D44/COUNTIFS('All Song Rankings'!$C:$C,A44,'All Song Rankings'!$F:$F,">=0")) -> 9.755102
A45: Off-list genres | B45: =$B$4-SUM(B23:B44) -> 7 | C45: =B45/$B$4 -> 0.0085784314

Sheet Repeated Songs
A1: Song | B1: Artist | C1: Round | D1: League | E1: Times Submitted | G1: Notes
A2: =IFERROR(INDEX('All Song Rankings'!$A:$A,MATCH(ROW()-1,'All Song Rankings'!$S:$S,0)),"") -> Shut Up and Dance | B2: =IFERROR(INDEX('All Song Rankings'!$B:$B,MATCH(ROW()-1,'All Song Rankings'!$S:$S,0)),"") -> WALK THE MOON | C2: =IFERROR(INDEX('All Song Rankings'!$E:$E,MATCH(ROW()-1,'All Song Rankings'!$S:$S,0)),"") -> 1 - A Song you'd recommend any day | D2: =IFERROR(INDEX('All Song Rankings'!$I:$I,MATCH(ROW()-1,'All Song Rankings'!$S:$S,0)),"") -> Org Mgmt COE (1st League) | E2: =IFERROR(INDEX('All Song Rankings'!$R:$R,MATCH(ROW()-1,'All Song Rankings'!$S:$S,0)),"") -> 2 | G2: Formula-driven from All Song Rankings (Repeat Count > 1). Lists up to 200 rows, in sheet order.
A3: =IFERROR(INDEX('All Song Rankings'!$A:$A,MATCH(ROW()-1,'All Song Rankings'!$S:$S,0)),"") -> Fantasy | B3: =IFERROR(INDEX('All Song Rankings'!$B:$B,MATCH(ROW()-1,'All Song Rankings'!$S:$S,0)),"") -> Mariah Carey | C3: =IFERROR(INDEX('All Song Rankings'!$E:$E,MATCH(ROW()-1,'All Song Rankings'!$S:$S,0)),"") -> 1 - A Song you'd recommend any day | D3: =IFERROR(INDEX('All Song Rankings'!$I:$I,MATCH(ROW()-1,'All Song Rankings'!$S:$S,0)),"") -> Org Mgmt COE (1st League) | E3: =IFERROR(INDEX('All Song Rankings'!$R:$R,MATCH(ROW()-1,'All Song Rankings'!$S:$S,0)),"") -> 2 | G3: A repeat = same Spotify URI (same recording) OR same Song + Artist text. Text matching also covers rows with no URI yet (e.g. League 8).
A4: =IFERROR(INDEX('All Song Rankings'!$A:$A,MATCH(ROW()-1,'All Song Rankings'!$S:$S,0)),"") -> Uptown Funk | B4: =IFERROR(INDEX('All Song Rankings'!$B:$B,MATCH(ROW()-1,'All Song Rankings'!$S:$S,0)),"") -> Mark Ronson | C4: =IFERROR(INDEX('All Song Rankings'!$E:$E,MATCH(ROW()-1,'All Song Rankings'!$S:$S,0)),"") -> 3 - Please Rise - You are now in charge of a country! What is the national anthem? | D4: =IFERROR(INDEX('All Song Rankings'!$I:$I,MATCH(ROW()-1,'All Song Rankings'!$S:$S,0)),"") -> Org Mgmt COE (1st League) | E4: =IFERROR(INDEX('All Song Rankings'!$R:$R,MATCH(ROW()-1,'All Song Rankings'!$S:$S,0)),"") -> 2
A5: =IFERROR(INDEX('All Song Rankings'!$A:$A,MATCH(ROW()-1,'All Song Rankings'!$S:$S,0)),"") -> drivers license | B5: =IFERROR(INDEX('All Song Rankings'!$B:$B,MATCH(ROW()-1,'All Song Rankings'!$S:$S,0)),"") -> Olivia Rodrigo | C5: =IFERROR(INDEX('All Song Rankings'!$E:$E,MATCH(ROW()-1,'All Song Rankings'!$S:$S,0)),"") -> 6 - Songs that tell a Story | D5: =IFERROR(INDEX('All Song Rankings'!$I:$I,MATCH(ROW()-1,'All Song Rankings'!$S:$S,0)),"") -> Org Mgmt COE (1st League) | E5: =IFERROR(INDEX('All Song Rankings'!$R:$R,MATCH(ROW()-1,'All Song Rankings'!$S:$S,0)),"") -> 3
A6: =IFERROR(INDEX('All Song Rankings'!$A:$A,MATCH(ROW()-1,'All Song Rankings'!$S:$S,0)),"") -> Golden | B6: =IFERROR(INDEX('All Song Rankings'!$B:$B,MATCH(ROW()-1,'All Song Rankings'!$S:$S,0)),"") -> HUNTR/X | C6: =IFERROR(INDEX('All Song Rankings'!$E:$E,MATCH(ROW()-1,'All Song Rankings'!$S:$S,0)),"") -> 8 - Best Earworm | D6: =IFERROR(INDEX('All Song Rankings'!$I:$I,MATCH(ROW()-1,'All Song Rankings'!$S:$S,0)),"") -> Org Mgmt COE (1st League) | E6: =IFERROR(INDEX('All Song Rankings'!$R:$R,MATCH(ROW()-1,'All Song Rankings'!$S:$S,0)),"") -> 2
A7: =IFERROR(INDEX('All Song Rankings'!$A:$A,MATCH(ROW()-1,'All Song Rankings'!$S:$S,0)),"") -> Uptown Funk | B7: =IFERROR(INDEX('All Song Rankings'!$B:$B,MATCH(ROW()-1,'All Song Rankings'!$S:$S,0)),"") -> Mark Ronson | C7: =IFERROR(INDEX('All Song Rankings'!$E:$E,MATCH(ROW()-1,'All Song Rankings'!$S:$S,0)),"") -> 8 - Best Earworm | D7: =IFERROR(INDEX('All Song Rankings'!$I:$I,MATCH(ROW()-1,'All Song Rankings'!$S:$S,0)),"") -> Org Mgmt COE (1st League) | E7: =IFERROR(INDEX('All Song Rankings'!$R:$R,MATCH(ROW()-1,'All Song Rankings'!$S:$S,0)),"") -> 2
A8: =IFERROR(INDEX('All Song Rankings'!$A:$A,MATCH(ROW()-1,'All Song Rankings'!$S:$S,0)),"") -> On The Floor | B8: =IFERROR(INDEX('All Song Rankings'!$B:$B,MATCH(ROW()-1,'All Song Rankings'!$S:$S,0)),"") -> Jennifer Lopez | C8: =IFERROR(INDEX('All Song Rankings'!$E:$E,MATCH(ROW()-1,'All Song Rankings'!$S:$S,0)),"") -> 1 - Workout Song | D8: =IFERROR(INDEX('All Song Rankings'!$I:$I,MATCH(ROW()-1,'All Song Rankings'!$S:$S,0)),"") -> Org Mgmt: The Sequel (2nd League) | E8: =IFERROR(INDEX('All Song Rankings'!$R:$R,MATCH(ROW()-1,'All Song Rankings'!$S:$S,0)),"") -> 2
A9: =IFERROR(INDEX('All Song Rankings'!$A:$A,MATCH(ROW()-1,'All Song Rankings'!$S:$S,0)),"") -> Misery Business | B9: =IFERROR(INDEX('All Song Rankings'!$B:$B,MATCH(ROW()-1,'All Song Rankings'!$S:$S,0)),"") -> Paramore | C9: =IFERROR(INDEX('All Song Rankings'!$E:$E,MATCH(ROW()-1,'All Song Rankings'!$S:$S,0)),"") -> 1 - Workout Song | D9: =IFERROR(INDEX('All Song Rankings'!$I:$I,MATCH(ROW()-1,'All Song Rankings'!$S:$S,0)),"") -> Org Mgmt: The Sequel (2nd League) | E9: =IFERROR(INDEX('All Song Rankings'!$R:$R,MATCH(ROW()-1,'All Song Rankings'!$S:$S,0)),"") -> 2
A10: =IFERROR(INDEX('All Song Rankings'!$A:$A,MATCH(ROW()-1,'All Song Rankings'!$S:$S,0)),"") -> drivers license | B10: =IFERROR(INDEX('All Song Rankings'!$B:$B,MATCH(ROW()-1,'All Song Rankings'!$S:$S,0)),"") -> Olivia Rodrigo | C10: =IFERROR(INDEX('All Song Rankings'!$E:$E,MATCH(ROW()-1,'All Song Rankings'!$S:$S,0)),"") -> 3 - Mystery (I'm Happy, Why Do You Ask?) | D10: =IFERROR(INDEX('All Song Rankings'!$I:$I,MATCH(ROW()-1,'All Song Rankings'!$S:$S,0)),"") -> Org Mgmt: The Sequel (2nd League) | E10: =IFERROR(INDEX('All Song Rankings'!$R:$R,MATCH(ROW()-1,'All Song Rankings'!$S:$S,0)),"") -> 3
A11: =IFERROR(INDEX('All Song Rankings'!$A:$A,MATCH(ROW()-1,'All Song Rankings'!$S:$S,0)),"") -> Rocket Man (I Think It's Going To Be a Long, Long Time) | B11: =IFERROR(INDEX('All Song Rankings'!$B:$B,MATCH(ROW()-1,'All Song Rankings'!$S:$S,0)),"") -> Elton John | C11: =IFERROR(INDEX('All Song Rankings'!$E:$E,MATCH(ROW()-1,'All Song Rankings'!$S:$S,0)),"") -> 4 - Songs from Another World | D11: =IFERROR(INDEX('All Song Rankings'!$I:$I,MATCH(ROW()-1,'All Song Rankings'!$S:$S,0)),"") -> Org Mgmt: The Sequel (2nd League) | E11: =IFERROR(INDEX('All Song Rankings'!$R:$R,MATCH(ROW()-1,'All Song Rankings'!$S:$S,0)),"") -> 2
A12: =IFERROR(INDEX('All Song Rankings'!$A:$A,MATCH(ROW()-1,'All Song Rankings'!$S:$S,0)),"") -> I Will Always Love You | B12: =IFERROR(INDEX('All Song Rankings'!$B:$B,MATCH(ROW()-1,'All Song Rankings'!$S:$S,0)),"") -> Whitney Houston | C12: =IFERROR(INDEX('All Song Rankings'!$E:$E,MATCH(ROW()-1,'All Song Rankings'!$S:$S,0)),"") -> 5 - The cover was better than the original | D12: =IFERROR(INDEX('All Song Rankings'!$I:$I,MATCH(ROW()-1,'All Song Rankings'!$S:$S,0)),"") -> Org Mgmt: The Sequel (2nd League) | E12: =IFERROR(INDEX('All Song Rankings'!$R:$R,MATCH(ROW()-1,'All Song Rankings'!$S:$S,0)),"") -> 2
A13: =IFERROR(INDEX('All Song Rankings'!$A:$A,MATCH(ROW()-1,'All Song Rankings'!$S:$S,0)),"") -> Sugar, We're Goin Down | B13: =IFERROR(INDEX('All Song Rankings'!$B:$B,MATCH(ROW()-1,'All Song Rankings'!$S:$S,0)),"") -> Fall Out Boy | C13: =IFERROR(INDEX('All Song Rankings'!$E:$E,MATCH(ROW()-1,'All Song Rankings'!$S:$S,0)),"") -> 6 - Forgotten Gems | D13: =IFERROR(INDEX('All Song Rankings'!$I:$I,MATCH(ROW()-1,'All Song Rankings'!$S:$S,0)),"") -> Org Mgmt: The Sequel (2nd League) | E13: =IFERROR(INDEX('All Song Rankings'!$R:$R,MATCH(ROW()-1,'All Song Rankings'!$S:$S,0)),"") -> 2
A14: =IFERROR(INDEX('All Song Rankings'!$A:$A,MATCH(ROW()-1,'All Song Rankings'!$S:$S,0)),"") -> Somebody That I Used To Know | B14: =IFERROR(INDEX('All Song Rankings'!$B:$B,MATCH(ROW()-1,'All Song Rankings'!$S:$S,0)),"") -> Gotye, Kimbra | C14: =IFERROR(INDEX('All Song Rankings'!$E:$E,MATCH(ROW()-1,'All Song Rankings'!$S:$S,0)),"") -> 6 - Forgotten Gems | D14: =IFERROR(INDEX('All Song Rankings'!$I:$I,MATCH(ROW()-1,'All Song Rankings'!$S:$S,0)),"") -> Org Mgmt: The Sequel (2nd League) | E14: =IFERROR(INDEX('All Song Rankings'!$R:$R,MATCH(ROW()-1,'All Song Rankings'!$S:$S,0)),"") -> 2
A15: =IFERROR(INDEX('All Song Rankings'!$A:$A,MATCH(ROW()-1,'All Song Rankings'!$S:$S,0)),"") -> Walk This Way (feat. Aerosmith) | B15: =IFERROR(INDEX('All Song Rankings'!$B:$B,MATCH(ROW()-1,'All Song Rankings'!$S:$S,0)),"") -> Run-D.M.C., Aerosmith | C15: =IFERROR(INDEX('All Song Rankings'!$E:$E,MATCH(ROW()-1,'All Song Rankings'!$S:$S,0)),"") -> 7 - Unexpected Collabs | D15: =IFERROR(INDEX('All Song Rankings'!$I:$I,MATCH(ROW()-1,'All Song Rankings'!$S:$S,0)),"") -> Org Mgmt: The Sequel (2nd League) | E15: =IFERROR(INDEX('All Song Rankings'!$R:$R,MATCH(ROW()-1,'All Song Rankings'!$S:$S,0)),"") -> 2
... A201: =IFERROR(INDEX('All Song Rankings'!$A:$A,MATCH(ROW()-1,'All Song Rankings'!$S:$S,0)),"") | B201: =IFERROR(INDEX('All Song Rankings'!$B:$B,MATCH(ROW()-1,'All Song Rankings'!$S:$S,0)),"") | C201: =IFERROR(INDEX('All Song Rankings'!$E:$E,MATCH(ROW()-1,'All Song Rankings'!$S:$S,0)),"") | D201: =IFERROR(INDEX('All Song Rankings'!$I:$I,MATCH(ROW()-1,'All Song Rankings'!$S:$S,0)),"") | E201: =IFERROR(INDEX('All Song Rankings'!$R:$R,MATCH(ROW()-1,'All Song Rankings'!$S:$S,0)),"")

Sheet Lists
A1: Genre | C1: About this list | E1: Genre Label | F1: Major Genre
A2: A Cappella | C2: Controlled genre list. The Genre column in All Song Rankings is validated against it (a warning, not a block). | E2: A Cappella | F2: Pop
A3: Alternative/Comedy | C3: Contains the 14 core labels plus 8 labels used 2+ times. Add a label here to allow it. | E3: Alternative Pop | F3: Pop
A4: Christian/Gospel | E4: Alternative/Comedy | F4: Rock
A5: Classical Crossover | C5: Columns E:F map every Genre label to a Major Genre (16 majors: the 14 core genres, Christian/Gospel, Other). PROPOSED mapping for the year-one recap; edit column F if you disagree. | E5: Children's Music | F5: Other
A6: Classical/Score | E6: Christian/Gospel | F6: Christian/Gospel
A7: Country | E7: Classical Crossover | F7: Classical/Score
A8: Disco | E8: Classical/Score | F8: Classical/Score
A9: Electronic/Dance | E9: Country | F9: Country
A10: Folk/Americana | E10: Disco | F10: Electronic/Dance
A11: Hip-Hop/Rap | E11: Electronic/Dance | F11: Electronic/Dance
A12: Indian Film Music | E12: Electronic/Pop | F12: Electronic/Dance
A13: Jazz/Vocal | E13: Experimental Rock | F13: Rock
A14: K-Pop | E14: Folk/Americana | F14: Folk/Americana
A15: Latin | E15: Hip-Hop/Classical Crossover | F15: Hip-Hop/Rap
A16: Metal | E16: Hip-Hop/Rap | F16: Hip-Hop/Rap
A17: Novelty | E17: Indian Film Music | F17: Soundtrack/Musical
... A23: Soundtrack/Musical | E23: Pop | F23: Pop
E24: Pop/Rock | F24: Pop
E25: Psychedelic Electronic | F25: Electronic/Dance
E26: R&B/Soul | F26: R&B/Soul
E27: Reggae | F27: Reggae
E28: Rock | F28: Rock
E29: Soundtrack/Musical | F29: Soundtrack/Musical
E30: Traditional Pop | F30: Other

Sheet Retired Artist
A1: Artist | B1: ArtistKey | C1: RetiredFlag | D1: RetiredDate
A2: 5 Seconds of Summer | B2: 5secondsofsummer | C2: Yes | D2: 46202
A3: ABBA | B3: abba | C3: Yes | D3: 46239
A4: Beyoncé | B4: beyonce | C4: Yes | D4: 46268
A5: Britney Spears | B5: britneyspears | C5: Yes | D5: 46247
A6: Coldplay | B6: coldplay | C6: Yes | D6: 46253
A7: Ed Sheeran | B7: edsheeran | C7: Yes | D7: 46202
A8: Eminem | B8: eminem | C8: Yes | D8: 46202
A9: Harry Styles | B9: harrystyles | C9: Yes | D9: 46202
A10: Jonas Brothers | B10: jonasbrothers | C10: Yes | D10: 46202
A11: Justin Bieber | B11: justinbieber | C11: Yes | D11: 46268
A12: Katy Perry | B12: katyperry | C12: Yes | D12: 46268
A13: Lady Gaga | B13: ladygaga | C13: Yes | D13: 46247
... A19: Whitney Houston | B19: whitneyhouston | C19: Yes | D19: 46231

Sheet Retired Songs
A1: Song | B1: Artist | C1: SongKey | D1: ArtistRetired | E1: RetiredDate | F1: Notes
A2: Bohemian Rhapsody | B2: Queen | C2: bohemianrhapsody | D2: No | E2: 46202
A3: Caramel | B3: Sleep Token | C3: caramel | D3: Yes | E3: 46202 | F3: Artist also retired
A4: Chicken Fried | B4: Zac Brown Band | C4: chickenfried | D4: No | E4: 46202
A5: drivers license | B5: Olivia Rodrigo | C5: driverslicense | D5: Yes | E5: 46202 | F5: Artist also retired
A6: Fantasy | B6: Mariah Carey | C6: fantasy | D6: Yes | E6: 46202 | F6: Artist also retired
A7: Golden | B7: HUNTR/X | C7: golden | D7: No | E7: 46202
A8: I Will Always Love You | B8: Whitney Houston | C8: iwillalwaysloveyou | D8: No | E8: 46202
A9: Misery Business | B9: Paramore | C9: miserybusiness | D9: No | E9: 46202
A10: Somebody That I Used to Know | B10: Gotye, Kimbra | C10: somebodythatiusedtoknow | D10: No | E10: 46202
A11: Uptown Funk | B11: Mark Ronson | C11: uptownfunk | D11: No | E11: 46202
A12: Walk This Way | B12: Aerosmith | C12: walkthisway | D12: No | E12: 46202 | F12: Includes Run-D.M.C. version
A13: On The Floor | B13: Jennifer Lopez | C13: onthefloor | D13: No | E13: 46224
A14: Raspberry Beret | B14: Prince | C14: raspberryberet | D14: No | E14: 46224
A15: I Want It That Way | B15: Backstreet Boys | C15: iwantitthatway | D15: No | E15: 46224
A16: Shut Up and Dance | B16: WALK THE MOON | C16: shutupanddance | D16: No | E16: 46224
A17: Billie Jean | B17: Michael Jackson | C17: billiejean | D17: No | E17: 46224
A18: Three Little Birds | B18: Bob Marley & The Wailers | C18: threelittlebirds | D18: No | E18: 46224
A19: Mr. Brightside | B19: The Killers | C19: mrbrightside | D19: No | E19: 46239
A20: Rocket Man (I Think It's Going To Be A Long, Long Time) | B20: Elton John | C20: rocketman | D20: No | E20: 46289
A21: Time Warp | B21: The Rocky Horror Show | C21: timewarp | D21: No | E21: 46289
A22: …Baby One More Time | B22: Britney Spears | C22: babyonemoretime | D22: Yes | E22: 46289 | F22: Artist also retired
A23: Dance Monkey | B23: Tones And I | C23: dancemonkey | D23: No | E23: 46289

Sheet Aliases
A1: Alias | B1: CanonicalArtist
A2: TS | B2: Taylor Swift
A3: Taylor | B3: Taylor Swift
A4: 5SOS | B4: 5 Seconds of Summer
A5: JB | B5: Jonas Brothers
A6: SleepToken | B6: Sleep Token
A7: Whitney | B7: Whitney Houston
A8: Gaga | B8: Lady Gaga
A9: Britney | B9: Britney Spears
A10: Michael | B10: Michael Jackson
A11: MJ | B11: Michael Jackson

Sheet Change Log
A1: Area | B1: League | C1: Round | D1: Item | E1: Before | F1: After | G1: Why
A2: Votes: repaired | B2: 1 | C2: 2 | D2: Kristen gave 2 point(s) | E2: Time Warp / Little Nell | F2: Time Warp / Little Nell, Patricia Quinn, Richard O'Brien, The Rocky Horror Picture Show | G2: Artist/title text differed from the rankings tab (accent or abbreviated artist list)
A3: Votes: repaired | B3: 1 | C3: 2 | D3: Logan gave 2 point(s) | E3: Time Warp / Little Nell | F3: Time Warp / Little Nell, Patricia Quinn, Richard O'Brien, The Rocky Horror Picture Show | G3: Artist/title text differed from the rankings tab (accent or abbreviated artist list)
A4: Votes: repaired | B4: 1 | C4: 2 | D4: Collin gave 1 point(s) | E4: Time Warp / Little Nell | F4: Time Warp / Little Nell, Patricia Quinn, Richard O'Brien, The Rocky Horror Picture Show | G4: Artist/title text differed from the rankings tab (accent or abbreviated artist list)
A5: Votes: repaired | B5: 1 | C5: 2 | D5: Matt gave 1 point(s) | E5: Time Warp / Little Nell | F5: Time Warp / Little Nell, Patricia Quinn, Richard O'Brien, The Rocky Horror Picture Show | G5: Artist/title text differed from the rankings tab (accent or abbreviated artist list)
A6: Votes: repaired | B6: 1 | C6: 2 | D6: Kelsey gave 1 point(s) | E6: Time Warp / Little Nell | F6: Time Warp / Little Nell, Patricia Quinn, Richard O'Brien, The Rocky Horror Picture Show | G6: Artist/title text differed from the rankings tab (accent or abbreviated artist list)
A7: Votes: repaired | B7: 1 | C7: 2 | D7: Stephanie gave 1 point(s) | E7: Time Warp / Little Nell | F7: Time Warp / Little Nell, Patricia Quinn, Richard O'Brien, The Rocky Horror Picture Show | G7: Artist/title text differed from the rankings tab (accent or abbreviated artist list)
A8: Votes: repaired | B8: 1 | C8: 2 | D8: Merita gave 1 point(s) | E8: Time Warp / Little Nell | F8: Time Warp / Little Nell, Patricia Quinn, Richard O'Brien, The Rocky Horror Picture Show | G8: Artist/title text differed from the rankings tab (accent or abbreviated artist list)
A9: Votes: repaired | B9: 1 | C9: 5 | D9: Olivia gave 1 point(s) | E9: F65 / Ed Sheeran | F9: F64 / Ed Sheeran | G9: Excel autofill incremented a number in the title/artist
A10: Votes: repaired | B10: 1 | C10: 5 | D10: Nicole gave 1 point(s) | E10: F66 / Ed Sheeran | F10: F64 / Ed Sheeran | G10: Excel autofill incremented a number in the title/artist
A11: Votes: repaired | B11: 1 | C11: 5 | D11: Stephanie gave 1 point(s) | E11: F67 / Ed Sheeran | F11: F64 / Ed Sheeran | G11: Excel autofill incremented a number in the title/artist
A12: Votes: repaired | B12: 2 | C12: 4 | D12: Merita gave 2 point(s) | E12: 2816 A.D. / Thomas Newman | F12: 2815 A.D. / Thomas Newman | G12: Excel autofill incremented a number in the title/artist
A13: Votes: repaired | B13: 2 | C13: 4 | D13: Maryann gave 1 point(s) | E13: 2817 A.D. / Thomas Newman | F13: 2815 A.D. / Thomas Newman | G13: Excel autofill incremented a number in the title/artist
... A87: Votes: kept from old tab | B87: 2 | C87: 7 | D87: Leah's ballot (2 point(s)) | E87: In old League 2 tab | F87: In Votes tab | G87: Missing from the platform export, but the official points include Leah's votes. Kept from your original tab.
A88: Rankings: artist spelling | D88: Artist | E88: A Day To Remember | F88: A Day to Remember | G88: Same artist was spelled two ways, which splits counts. Standardised to the artist's own styling.
A89: Rankings: artist spelling | D89: Artist | E89: MGK | F89: mgk | G89: Same artist was spelled two ways, which splits counts. Standardised to the artist's own styling.
A90: Rankings: # of Voters | B90: 2 | C90: 7 | D90: Walk This Way (feat. Aerosmith) | E90: 7 | F90: 8 | G90: Points reconcile only with Leah's ballot included, which makes 1 more voter than was typed. Revert if the site shows the old number.
A91: Rankings: # of Voters | B91: 2 | C91: 7 | D91: Pour Me A Drink (Feat. Blake Shelton) | E91: 4 | F91: 5 | G91: Points reconcile only with Leah's ballot included, which makes 1 more voter than was typed. Revert if the site shows the old number.
A92: Rankings: # of Voters | B92: 2 | C92: 7 | D92: BLOW (with Chris Stapleton & Bruno Mars) | E92: 3 | F92: 4 | G92: Points reconcile only with Leah's ballot included, which makes 1 more voter than was typed. Revert if the site shows the old number.
A93: Rankings: # of Voters | B93: 2 | C93: 7 | D93: Over And Over | E93: 3 | F93: 4 | G93: Points reconcile only with Leah's ballot included, which makes 1 more voter than was typed. Revert if the site shows the old number.
A94: Rankings: # of Voters | B94: 2 | C94: 7 | D94: All The Way (feat. Bailey Zimmerman) | E94: 3 | F94: 4 | G94: Points reconcile only with Leah's ballot included, which makes 1 more voter than was typed. Revert if the site shows the old number.
A95: Structure: removed | D95: League 1-7 Votes tabs (7) | E95: 7 tabs | F95: 1 Votes tab | G95: Replaced by one Votes table keyed by League # + Round # + Spotify URI.
A96: Structure: removed | D96: Old Music League Analytics pivots | E96: 2 stale pivots | F96: Formula-driven tab | G96: Pivot cache held 786 of 816 rows and no Genre field.
A97: Structure: replaced | D97: Repeated Songs tab | E97: Static paste (46 rows) | F97: Formula-driven | G97: Old tab missed Gabriela, Head Over Heels, Sugar We're Goin Down and You Make My Dreams Come True. It also listed a few near-matches (different recordings or title spellings) that exact matching does not flag.
A98: Structure: added | D98: Rounds, Participants, Lists, Checks, README, Change Log | E98: - | F98: New tabs | G98: Options 2 to 4 of the proposed update.
A99: Structure: added columns | D99: All Song Rankings: League #, Round #, Spotify URI, Subgenre, Place #, Raw Points, Raw Voters, Status, Repeat Count, Repeat Seq, Key | E99: Columns A:I | F99: Columns A:T | G99: Columns A:I are unchanged in meaning; Place is now league-aware and works without LET.
A100: Open item | B100: 2 | D100: Export has a 9th round ('Your Villain Theme Song') with one submission | E100: In export | F100: Not in workbook | G100: The workbook numbers League 2 as 8 rounds. That submission (The Future Soon, Shayne) is not included.
A101: Structure: added | D101: Lists: Genre Label to Major Genre mapping (tblMajorGenres); All Song Rankings: Major Genre column | E101: - | F101: 15 non-core labels mapped | G101: PROPOSED defaults for the year-one recap (e.g. Pop/Rock to Pop, Disco to Electronic/Dance). Edit Lists column F to change.
A102: Structure: added | D102: Rounds: Max Votes per Song (blank) | E102: - | F102: Input column | G102: Needed to normalize scores for the recap. Fill in from each league's settings; blank is treated as 1.
A103: Open item | B103: 8 | D103: League 8: Spotify URI, Submitter blank | E103: - | F103: - | G103: Fill in once the rounds are revealed and exported.
A104: Open item | B104: 6 | C104: 2 | D104: Joy to the World (Three Dog Night) | E104: Workbook title | F104: Spotify title: Jeremiah Was a Bullfrog | G104: Spotify lists that track under a different title. Left as typed.
A105: Open item | D105: 7 genres not on the Lists tab | E105: Genre column | F105: Unchanged (highlighted) | G105: One-off labels such as Electronic/Pop. Review and map to the list if you want.
A106: Open item | D106: Retired Artist / Retired Songs / Aliases | E106: - | F106: Copied unchanged | G106: Not enforced by any formula. Stray conditional formats on Retired Songs were dropped.
A107: Open item | D107: Zero-point votes | E107: In exports | F107: Not stored | G107: Same as the old tabs. A voter's participation is inferred from their other votes in the round.
